{
"meta":{"test_sets":[],"test_metrics":[],"learn_metrics":[{"best_value":"Min","name":"RMSE"}],"launch_mode":"Train","parameters":"","iteration_count":1000,"learn_sets":["learn"],"name":"experiment"},
"iterations":[
{"learn":[14.61268541],"iteration":0,"passed_time":0.1626268885,"remaining_time":162.4642616},
{"learn":[14.23196558],"iteration":1,"passed_time":0.1632100365,"remaining_time":81.4418082},
{"learn":[13.86674177],"iteration":2,"passed_time":0.1637626726,"remaining_time":54.42379487},
{"learn":[13.49946468],"iteration":3,"passed_time":0.1642862953,"remaining_time":40.90728753},
{"learn":[13.16661202],"iteration":4,"passed_time":0.1648450299,"remaining_time":32.80416095},
{"learn":[12.85632158],"iteration":5,"passed_time":0.1654243301,"remaining_time":27.40529735},
{"learn":[12.56784336],"iteration":6,"passed_time":0.1659536098,"remaining_time":23.54170493},
{"learn":[12.31617801],"iteration":7,"passed_time":0.1664981524,"remaining_time":20.6457709},
{"learn":[12.01509946],"iteration":8,"passed_time":0.1670532001,"remaining_time":18.39441348},
{"learn":[11.71512571],"iteration":9,"passed_time":0.1675901994,"remaining_time":16.59142974},
{"learn":[11.43264457],"iteration":10,"passed_time":0.1680883232,"remaining_time":15.11266833},
{"learn":[11.17973129],"iteration":11,"passed_time":0.1685782496,"remaining_time":13.87960922},
{"learn":[10.93746433],"iteration":12,"passed_time":0.1690587364,"remaining_time":12.83545945},
{"learn":[10.69387075],"iteration":13,"passed_time":0.1695793784,"remaining_time":11.94323337},
{"learn":[10.4615922],"iteration":14,"passed_time":0.1700850188,"remaining_time":11.16891623},
{"learn":[10.2299235],"iteration":15,"passed_time":0.1705809337,"remaining_time":10.49072742},
{"learn":[10.01419731],"iteration":16,"passed_time":0.1711080681,"remaining_time":9.894072407},
{"learn":[9.795856918],"iteration":17,"passed_time":0.171606791,"remaining_time":9.362103821},
{"learn":[9.60040151],"iteration":18,"passed_time":0.1720910622,"remaining_time":8.885333263},
{"learn":[9.418664989],"iteration":19,"passed_time":0.172626172,"remaining_time":8.458682428},
{"learn":[9.249278645],"iteration":20,"passed_time":0.1731246858,"remaining_time":8.070907973},
{"learn":[9.090113396],"iteration":21,"passed_time":0.1736041567,"remaining_time":7.717493877},
{"learn":[8.909548708],"iteration":22,"passed_time":0.1741032697,"remaining_time":7.395604109},
{"learn":[8.740140208],"iteration":23,"passed_time":0.1746149382,"remaining_time":7.101007486},
{"learn":[8.59377682],"iteration":24,"passed_time":0.1751050498,"remaining_time":6.829096942},
{"learn":[8.453885414],"iteration":25,"passed_time":0.1755963604,"remaining_time":6.578109808},
{"learn":[8.317732234],"iteration":26,"passed_time":0.1761081259,"remaining_time":6.346415056},
{"learn":[8.180896085],"iteration":27,"passed_time":0.1766108273,"remaining_time":6.130918719},
{"learn":[8.053220863],"iteration":28,"passed_time":0.1771065299,"remaining_time":5.930015191},
{"learn":[7.924234474],"iteration":29,"passed_time":0.1776180078,"remaining_time":5.742982253},
{"learn":[7.818879511],"iteration":30,"passed_time":0.1781121635,"remaining_time":5.567441499},
{"learn":[7.719346395],"iteration":31,"passed_time":0.1785956404,"remaining_time":5.402518121},
{"learn":[7.624163594],"iteration":32,"passed_time":0.1790891159,"remaining_time":5.247853791},
{"learn":[7.524952543],"iteration":33,"passed_time":0.1796163609,"remaining_time":5.103217784},
{"learn":[7.424464745],"iteration":34,"passed_time":0.1801147891,"remaining_time":4.966022043},
{"learn":[7.327482321],"iteration":35,"passed_time":0.1806052822,"remaining_time":4.836208112},
{"learn":[7.238666841],"iteration":36,"passed_time":0.1811128334,"remaining_time":4.71382861},
{"learn":[7.158842395],"iteration":37,"passed_time":0.1816340274,"remaining_time":4.5982088},
{"learn":[7.074348246],"iteration":38,"passed_time":0.1821765532,"remaining_time":4.489017118},
{"learn":[6.992269093],"iteration":39,"passed_time":0.1826801556,"remaining_time":4.384323734},
{"learn":[6.925219745],"iteration":40,"passed_time":0.1831904488,"remaining_time":4.284869277},
{"learn":[6.86013671],"iteration":41,"passed_time":0.1836967939,"remaining_time":4.190036394},
{"learn":[6.786739622],"iteration":42,"passed_time":0.184215779,"remaining_time":4.099872106},
{"learn":[6.73057926],"iteration":43,"passed_time":0.1847260573,"remaining_time":4.013593426},
{"learn":[6.666356486],"iteration":44,"passed_time":0.185214066,"remaining_time":3.930654067},
{"learn":[6.606182832],"iteration":45,"passed_time":0.1857585775,"remaining_time":3.852471369},
{"learn":[6.547854615],"iteration":46,"passed_time":0.1862942544,"remaining_time":3.777413286},
{"learn":[6.49240675],"iteration":47,"passed_time":0.1867945549,"remaining_time":3.704758673},
{"learn":[6.431317261],"iteration":48,"passed_time":0.1873033737,"remaining_time":3.635214456},
{"learn":[6.377586395],"iteration":49,"passed_time":0.1878123023,"remaining_time":3.568433743},
{"learn":[6.327558015],"iteration":50,"passed_time":0.1883012067,"remaining_time":3.503879317},
{"learn":[6.282040317],"iteration":51,"passed_time":0.1888349627,"remaining_time":3.442606627},
{"learn":[6.237655841],"iteration":52,"passed_time":0.1893606137,"remaining_time":3.383481153},
{"learn":[6.192792003],"iteration":53,"passed_time":0.1898499452,"remaining_time":3.325889781},
{"learn":[6.150579347],"iteration":54,"passed_time":0.1903990907,"remaining_time":3.271402559},
{"learn":[6.115693845],"iteration":55,"passed_time":0.1908994591,"remaining_time":3.218019453},
{"learn":[6.078780782],"iteration":56,"passed_time":0.1914109869,"remaining_time":3.166676503},
{"learn":[6.045146957],"iteration":57,"passed_time":0.1919494985,"remaining_time":3.117524614},
{"learn":[6.008080327],"iteration":58,"passed_time":0.192460221,"remaining_time":3.069577423},
{"learn":[5.977575734],"iteration":59,"passed_time":0.1929455574,"remaining_time":3.022813732},
{"learn":[5.948036502],"iteration":60,"passed_time":0.1934312313,"remaining_time":2.97757256},
{"learn":[5.914888282],"iteration":61,"passed_time":0.1939483048,"remaining_time":2.93425016},
{"learn":[5.884957796],"iteration":62,"passed_time":0.1944309192,"remaining_time":2.891774147},
{"learn":[5.849539885],"iteration":63,"passed_time":0.1949154887,"remaining_time":2.850639022},
{"learn":[5.821387627],"iteration":64,"passed_time":0.1954264392,"remaining_time":2.811134163},
{"learn":[5.797012279],"iteration":65,"passed_time":0.1959474476,"remaining_time":2.772953274},
{"learn":[5.768685095],"iteration":66,"passed_time":0.1964669185,"remaining_time":2.735875148},
{"learn":[5.755484587],"iteration":67,"passed_time":0.1967952112,"remaining_time":2.697252013},
{"learn":[5.731887055],"iteration":68,"passed_time":0.1972866999,"remaining_time":2.661940835},
{"learn":[5.707148487],"iteration":69,"passed_time":0.1978211271,"remaining_time":2.628194974},
{"learn":[5.685365039],"iteration":70,"passed_time":0.1983322878,"remaining_time":2.595080216},
{"learn":[5.663541834],"iteration":71,"passed_time":0.198828931,"remaining_time":2.562684},
{"learn":[5.638108797],"iteration":72,"passed_time":0.199315856,"remaining_time":2.531038336},
{"learn":[5.619204893],"iteration":73,"passed_time":0.1998176724,"remaining_time":2.500421144},
{"learn":[5.598472793],"iteration":74,"passed_time":0.2003211553,"remaining_time":2.470627582},
{"learn":[5.577007075],"iteration":75,"passed_time":0.2008522809,"remaining_time":2.441940889},
{"learn":[5.562637084],"iteration":76,"passed_time":0.2013733551,"remaining_time":2.413865023},
{"learn":[5.54729991],"iteration":77,"passed_time":0.2018633621,"remaining_time":2.38612846},
{"learn":[5.530737623],"iteration":78,"passed_time":0.2023919935,"remaining_time":2.359531975},
{"learn":[5.513704873],"iteration":79,"passed_time":0.2028778033,"remaining_time":2.333094738},
{"learn":[5.501575529],"iteration":80,"passed_time":0.2033828606,"remaining_time":2.307516653},
{"learn":[5.484080734],"iteration":81,"passed_time":0.2038772065,"remaining_time":2.28243019},
{"learn":[5.472178894],"iteration":82,"passed_time":0.2043705732,"remaining_time":2.25792549},
{"learn":[5.458923342],"iteration":83,"passed_time":0.2048587736,"remaining_time":2.23393615},
{"learn":[5.451382371],"iteration":84,"passed_time":0.2052059123,"remaining_time":2.208981291},
{"learn":[5.441410748],"iteration":85,"passed_time":0.2056826976,"remaining_time":2.185976577},
{"learn":[5.434047468],"iteration":86,"passed_time":0.2060125379,"remaining_time":2.161947668},
{"learn":[5.422107497],"iteration":87,"passed_time":0.2065435109,"remaining_time":2.14054184},
{"learn":[5.40731265],"iteration":88,"passed_time":0.2070750865,"remaining_time":2.119611279},
{"learn":[5.396360181],"iteration":89,"passed_time":0.2075757364,"remaining_time":2.098821335},
{"learn":[5.383793239],"iteration":90,"passed_time":0.2080675998,"remaining_time":2.078389541},
{"learn":[5.369605034],"iteration":91,"passed_time":0.2085678946,"remaining_time":2.058474438},
{"learn":[5.357467333],"iteration":92,"passed_time":0.20908024,"remaining_time":2.039094384},
{"learn":[5.341109968],"iteration":93,"passed_time":0.2095855513,"remaining_time":2.020047973},
{"learn":[5.330529276],"iteration":94,"passed_time":0.2100765789,"remaining_time":2.001255831},
{"learn":[5.319862075],"iteration":95,"passed_time":0.2105804643,"remaining_time":1.982966039},
{"learn":[5.313052243],"iteration":96,"passed_time":0.2111541313,"remaining_time":1.965692584},
{"learn":[5.299677207],"iteration":97,"passed_time":0.2117209595,"remaining_time":1.948696994},
{"learn":[5.287546698],"iteration":98,"passed_time":0.2122439288,"remaining_time":1.93163414},
{"learn":[5.279803754],"iteration":99,"passed_time":0.2127984948,"remaining_time":1.915186453},
{"learn":[5.272254612],"iteration":100,"passed_time":0.2133614023,"remaining_time":1.899127729},
{"learn":[5.268813888],"iteration":101,"passed_time":0.2136599818,"remaining_time":1.881045722},
{"learn":[5.258113767],"iteration":102,"passed_time":0.2141838682,"remaining_time":1.865271163},
{"learn":[5.251018576],"iteration":103,"passed_time":0.2147330512,"remaining_time":1.850007826},
{"learn":[5.24171237],"iteration":104,"passed_time":0.215258902,"remaining_time":1.834825879},
{"learn":[5.233984943],"iteration":105,"passed_time":0.2157827106,"remaining_time":1.819903239},
{"learn":[5.226240449],"iteration":106,"passed_time":0.2163308941,"remaining_time":1.805453163},
{"learn":[5.220541644],"iteration":107,"passed_time":0.2168375157,"remaining_time":1.79091726},
{"learn":[5.211712096],"iteration":108,"passed_time":0.2173802213,"remaining_time":1.776933736},
{"learn":[5.203388597],"iteration":109,"passed_time":0.2179025523,"remaining_time":1.763029741},
{"learn":[5.196026544],"iteration":110,"passed_time":0.2184108478,"remaining_time":1.749254448},
{"learn":[5.188716772],"iteration":111,"passed_time":0.2189511058,"remaining_time":1.735969482},
{"learn":[5.182163132],"iteration":112,"passed_time":0.2194959007,"remaining_time":1.722945699},
{"learn":[5.17764747],"iteration":113,"passed_time":0.2200114859,"remaining_time":1.709913829},
{"learn":[5.170548056],"iteration":114,"passed_time":0.2205206244,"remaining_time":1.697050022},
{"learn":[5.165901827],"iteration":115,"passed_time":0.220946217,"remaining_time":1.683762551},
{"learn":[5.160333668],"iteration":116,"passed_time":0.2214490247,"remaining_time":1.671277683},
{"learn":[5.148953243],"iteration":117,"passed_time":0.2219485085,"remaining_time":1.658971055},
{"learn":[5.144729126],"iteration":118,"passed_time":0.2223656069,"remaining_time":1.646252938},
{"learn":[5.139939946],"iteration":119,"passed_time":0.2228624949,"remaining_time":1.634324963},
{"learn":[5.132898872],"iteration":120,"passed_time":0.2233566492,"remaining_time":1.622566071},
{"learn":[5.129073077],"iteration":121,"passed_time":0.2238729145,"remaining_time":1.611150975},
{"learn":[5.127123916],"iteration":122,"passed_time":0.2241381888,"remaining_time":1.598123509},
{"learn":[5.121282057],"iteration":123,"passed_time":0.2246327342,"remaining_time":1.586921574},
{"learn":[5.114489821],"iteration":124,"passed_time":0.225197983,"remaining_time":1.576385881},
{"learn":[5.107777291],"iteration":125,"passed_time":0.2257746325,"remaining_time":1.56608753},
{"learn":[5.103518754],"iteration":126,"passed_time":0.2263193485,"remaining_time":1.555722766},
{"learn":[5.101133351],"iteration":127,"passed_time":0.22665376,"remaining_time":1.54407874},
{"learn":[5.096462705],"iteration":128,"passed_time":0.2271936965,"remaining_time":1.533997749},
{"learn":[5.08562082],"iteration":129,"passed_time":0.2277237913,"remaining_time":1.52399768},
{"learn":[5.080483682],"iteration":130,"passed_time":0.2282447055,"remaining_time":1.514081291},
{"learn":[5.07437499],"iteration":131,"passed_time":0.2287821259,"remaining_time":1.504415798},
{"learn":[5.070683732],"iteration":132,"passed_time":0.2292900254,"remaining_time":1.494695128},
{"learn":[5.06432037],"iteration":133,"passed_time":0.2298408484,"remaining_time":1.485389364},
{"learn":[5.057436484],"iteration":134,"passed_time":0.2303795916,"remaining_time":1.476135902},
{"learn":[5.053254656],"iteration":135,"passed_time":0.2308773001,"remaining_time":1.466749906},
{"learn":[5.04801663],"iteration":136,"passed_time":0.2313604836,"remaining_time":1.45740217},
{"learn":[5.045680836],"iteration":137,"passed_time":0.2317857223,"remaining_time":1.447820961},
{"learn":[5.041857933],"iteration":138,"passed_time":0.2322997131,"remaining_time":1.438921244},
{"learn":[5.035264888],"iteration":139,"passed_time":0.2327718655,"remaining_time":1.429884317},
{"learn":[5.028771948],"iteration":140,"passed_time":0.2333069154,"remaining_time":1.421352059},
{"learn":[5.024912247],"iteration":141,"passed_time":0.2338028396,"remaining_time":1.412696031},
{"learn":[5.02239068],"iteration":142,"passed_time":0.2342808582,"remaining_time":1.404046821},
{"learn":[5.017110572],"iteration":143,"passed_time":0.2347989744,"remaining_time":1.395749459},
{"learn":[5.010707886],"iteration":144,"passed_time":0.2353219295,"remaining_time":1.387587929},
{"learn":[5.004389868],"iteration":145,"passed_time":0.2358190049,"remaining_time":1.379379659},
{"learn":[4.997628683],"iteration":146,"passed_time":0.2363235194,"remaining_time":1.371319469},
{"learn":[4.991497851],"iteration":147,"passed_time":0.2368192459,"remaining_time":1.363310794},
{"learn":[4.988345253],"iteration":148,"passed_time":0.2373159505,"remaining_time":1.35540855},
{"learn":[4.98460423],"iteration":149,"passed_time":0.2378317113,"remaining_time":1.34771303},
{"learn":[4.982441783],"iteration":150,"passed_time":0.238352506,"remaining_time":1.340140911},
{"learn":[4.977461771],"iteration":151,"passed_time":0.2388539345,"remaining_time":1.332553529},
{"learn":[4.973601586],"iteration":152,"passed_time":0.2393484285,"remaining_time":1.325020385},
{"learn":[4.968328804],"iteration":153,"passed_time":0.239935764,"remaining_time":1.318088678},
{"learn":[4.9640736],"iteration":154,"passed_time":0.24052558,"remaining_time":1.311252355},
{"learn":[4.960865882],"iteration":155,"passed_time":0.2410505522,"remaining_time":1.304145295},
{"learn":[4.957014156],"iteration":156,"passed_time":0.2415724878,"remaining_time":1.297105778},
{"learn":[4.952244852],"iteration":157,"passed_time":0.2420710423,"remaining_time":1.290024162},
{"learn":[4.949695675],"iteration":158,"passed_time":0.2425530964,"remaining_time":1.282938076},
{"learn":[4.946584698],"iteration":159,"passed_time":0.2430561443,"remaining_time":1.276044757},
{"learn":[4.940192834],"iteration":160,"passed_time":0.2435977229,"remaining_time":1.269431612},
{"learn":[4.936727994],"iteration":161,"passed_time":0.2440928432,"remaining_time":1.262653102},
{"learn":[4.932342063],"iteration":162,"passed_time":0.2446187743,"remaining_time":1.256109902},
{"learn":[4.925830838],"iteration":163,"passed_time":0.2451254316,"remaining_time":1.249541834},
{"learn":[4.922571773],"iteration":164,"passed_time":0.2456332041,"remaining_time":1.243052881},
{"learn":[4.918395814],"iteration":165,"passed_time":0.2461396066,"remaining_time":1.236629108},
{"learn":[4.911142452],"iteration":166,"passed_time":0.2466464938,"remaining_time":1.230278619},
{"learn":[4.908276131],"iteration":167,"passed_time":0.2471380481,"remaining_time":1.223921762},
{"learn":[4.904584645],"iteration":168,"passed_time":0.2476386559,"remaining_time":1.217678834},
{"learn":[4.89795517],"iteration":169,"passed_time":0.2481499571,"remaining_time":1.211555673},
{"learn":[4.895556491],"iteration":170,"passed_time":0.2486650392,"remaining_time":1.205516476},
{"learn":[4.890591233],"iteration":171,"passed_time":0.2491760518,"remaining_time":1.199521924},
{"learn":[4.884629277],"iteration":172,"passed_time":0.2496628772,"remaining_time":1.193475141},
{"learn":[4.880550786],"iteration":173,"passed_time":0.2501577095,"remaining_time":1.187530276},
{"learn":[4.876384842],"iteration":174,"passed_time":0.2506489048,"remaining_time":1.181630551},
{"learn":[4.872638238],"iteration":175,"passed_time":0.2511817737,"remaining_time":1.175987395},
{"learn":[4.869137118],"iteration":176,"passed_time":0.2516520784,"remaining_time":1.170111076},
{"learn":[4.863587157],"iteration":177,"passed_time":0.2521601003,"remaining_time":1.164469677},
{"learn":[4.858028614],"iteration":178,"passed_time":0.2526600672,"remaining_time":1.158848688},
{"learn":[4.853838176],"iteration":179,"passed_time":0.2531504814,"remaining_time":1.153241082},
{"learn":[4.853462329],"iteration":180,"passed_time":0.2534058412,"remaining_time":1.146626431},
{"learn":[4.851573196],"iteration":181,"passed_time":0.2539437116,"remaining_time":1.141351407},
{"learn":[4.848442087],"iteration":182,"passed_time":0.2544618753,"remaining_time":1.136040175},
{"learn":[4.845547104],"iteration":183,"passed_time":0.2549569877,"remaining_time":1.130678815},
{"learn":[4.839868817],"iteration":184,"passed_time":0.2554892642,"remaining_time":1.125533785},
{"learn":[4.836336958],"iteration":185,"passed_time":0.2559899062,"remaining_time":1.120299912},
{"learn":[4.831124789],"iteration":186,"passed_time":0.2564947197,"remaining_time":1.115134798},
{"learn":[4.827407333],"iteration":187,"passed_time":0.2569910593,"remaining_time":1.10998266},
{"learn":[4.824088918],"iteration":188,"passed_time":0.2574754304,"remaining_time":1.104828434},
{"learn":[4.820934539],"iteration":189,"passed_time":0.257978312,"remaining_time":1.099802277},
{"learn":[4.816975227],"iteration":190,"passed_time":0.2584675864,"remaining_time":1.09476585},
{"learn":[4.812340486],"iteration":191,"passed_time":0.2589605139,"remaining_time":1.089792163},
{"learn":[4.806402747],"iteration":192,"passed_time":0.2594498836,"remaining_time":1.084850031},
{"learn":[4.801521788],"iteration":193,"passed_time":0.2599364771,"remaining_time":1.079942271},
{"learn":[4.797601172],"iteration":194,"passed_time":0.2604456691,"remaining_time":1.075173147},
{"learn":[4.792694629],"iteration":195,"passed_time":0.2609403936,"remaining_time":1.070388145},
{"learn":[4.789794613],"iteration":196,"passed_time":0.2614271669,"remaining_time":1.06561429},
{"learn":[4.785367055],"iteration":197,"passed_time":0.2619023261,"remaining_time":1.060836695},
{"learn":[4.780376856],"iteration":198,"passed_time":0.2623949999,"remaining_time":1.056172839},
{"learn":[4.776691261],"iteration":199,"passed_time":0.262871438,"remaining_time":1.051485752},
{"learn":[4.773470753],"iteration":200,"passed_time":0.2633823021,"remaining_time":1.04697741},
{"learn":[4.77207327],"iteration":201,"passed_time":0.2638606058,"remaining_time":1.042380017},
{"learn":[4.767347177],"iteration":202,"passed_time":0.2643903619,"remaining_time":1.038025214},
{"learn":[4.763983068],"iteration":203,"passed_time":0.264890053,"remaining_time":1.033590599},
{"learn":[4.761588849],"iteration":204,"passed_time":0.2653765219,"remaining_time":1.029143097},
{"learn":[4.758558086],"iteration":205,"passed_time":0.2658534239,"remaining_time":1.024697178},
{"learn":[4.753678804],"iteration":206,"passed_time":0.2663479657,"remaining_time":1.020357183},
{"learn":[4.746510889],"iteration":207,"passed_time":0.2668636523,"remaining_time":1.016134676},
{"learn":[4.744840601],"iteration":208,"passed_time":0.2673332807,"remaining_time":1.011773326},
{"learn":[4.741702222],"iteration":209,"passed_time":0.2678282361,"remaining_time":1.007544317},
{"learn":[4.739352853],"iteration":210,"passed_time":0.2683826126,"remaining_time":1.003572897},
{"learn":[4.735539287],"iteration":211,"passed_time":0.2689320971,"remaining_time":0.9996155308},
{"learn":[4.730726751],"iteration":212,"passed_time":0.2694633206,"remaining_time":0.9956226915},
{"learn":[4.726416092],"iteration":213,"passed_time":0.2700158682,"remaining_time":0.9917405254},
{"learn":[4.721293082],"iteration":214,"passed_time":0.2705611113,"remaining_time":0.9878626622},
{"learn":[4.718443695],"iteration":215,"passed_time":0.2711280861,"remaining_time":0.9840945348},
{"learn":[4.711627962],"iteration":216,"passed_time":0.2717029789,"remaining_time":0.9803844814},
{"learn":[4.709790764],"iteration":217,"passed_time":0.272208671,"remaining_time":0.9764549573},
{"learn":[4.706913073],"iteration":218,"passed_time":0.2728210472,"remaining_time":0.9729371592},
{"learn":[4.703846389],"iteration":219,"passed_time":0.2734048992,"remaining_time":0.9693446428},
{"learn":[4.701001135],"iteration":220,"passed_time":0.2739859561,"remaining_time":0.9657695015},
{"learn":[4.700380864],"iteration":221,"passed_time":0.2745139876,"remaining_time":0.9620355062},
{"learn":[4.695837486],"iteration":222,"passed_time":0.2750646026,"remaining_time":0.9584089517},
{"learn":[4.691242996],"iteration":223,"passed_time":0.2756612614,"remaining_time":0.9549693697},
{"learn":[4.690284609],"iteration":224,"passed_time":0.2762016289,"remaining_time":0.9513611663},
{"learn":[4.68827119],"iteration":225,"passed_time":0.2767814104,"remaining_time":0.9479150959},
{"learn":[4.686922425],"iteration":226,"passed_time":0.2773043205,"remaining_time":0.9443006157},
{"learn":[4.686085874],"iteration":227,"passed_time":0.2777927828,"remaining_time":0.9405966155},
{"learn":[4.683230741],"iteration":228,"passed_time":0.2783008079,"remaining_time":0.9369865629},
{"learn":[4.6773487],"iteration":229,"passed_time":0.2788820318,"remaining_time":0.9336485412},
{"learn":[4.671462906],"iteration":230,"passed_time":0.2794536402,"remaining_time":0.930302378},
{"learn":[4.664799601],"iteration":231,"passed_time":0.2800194835,"remaining_time":0.9269610487},
{"learn":[4.660979386],"iteration":232,"passed_time":0.2805337826,"remaining_time":0.923473868},
{"learn":[4.656281279],"iteration":233,"passed_time":0.2810725111,"remaining_time":0.9200920664},
{"learn":[4.651997094],"iteration":234,"passed_time":0.2816408252,"remaining_time":0.9168307713},
{"learn":[4.650151977],"iteration":235,"passed_time":0.2821528262,"remaining_time":0.9134099967},
{"learn":[4.648478046],"iteration":236,"passed_time":0.2826964853,"remaining_time":0.9101156889},
{"learn":[4.646364602],"iteration":237,"passed_time":0.2832583112,"remaining_time":0.9069026602},
{"learn":[4.642635873],"iteration":238,"passed_time":0.2837789657,"remaining_time":0.9035807234},
{"learn":[4.640860821],"iteration":239,"passed_time":0.2842605198,"remaining_time":0.9001583128},
{"learn":[4.639446822],"iteration":240,"passed_time":0.2847770549,"remaining_time":0.8968704759},
{"learn":[4.637120072],"iteration":241,"passed_time":0.2852795219,"remaining_time":0.8935614776},
{"learn":[4.633769267],"iteration":242,"passed_time":0.2857773281,"remaining_time":0.8902610591},
{"learn":[4.630491517],"iteration":243,"passed_time":0.2862998603,"remaining_time":0.8870602228},
{"learn":[4.627813333],"iteration":244,"passed_time":0.2868129822,"remaining_time":0.8838522511},
{"learn":[4.622496304],"iteration":245,"passed_time":0.2873152639,"remaining_time":0.8806329633},
{"learn":[4.618979301],"iteration":246,"passed_time":0.2878148978,"remaining_time":0.8774276035},
{"learn":[4.616563458],"iteration":247,"passed_time":0.2883486242,"remaining_time":0.8743474411},
{"learn":[4.614759385],"iteration":248,"passed_time":0.2888387943,"remaining_time":0.8711563635},
{"learn":[4.61251363],"iteration":249,"passed_time":0.2893319837,"remaining_time":0.867995951},
{"learn":[4.608796693],"iteration":250,"passed_time":0.2898289138,"remaining_time":0.864867954},
{"learn":[4.60847774],"iteration":251,"passed_time":0.2903300451,"remaining_time":0.8617733085},
{"learn":[4.605195659],"iteration":252,"passed_time":0.2908142774,"remaining_time":0.8586492696},
{"learn":[4.60103766],"iteration":253,"passed_time":0.2912964264,"remaining_time":0.855539898},
{"learn":[4.599325598],"iteration":254,"passed_time":0.2917956585,"remaining_time":0.8525010416},
{"learn":[4.597012808],"iteration":255,"passed_time":0.2923019076,"remaining_time":0.8495024191},
{"learn":[4.594161533],"iteration":256,"passed_time":0.2928182226,"remaining_time":0.8465522933},
{"learn":[4.592197259],"iteration":257,"passed_time":0.2933028078,"remaining_time":0.8435297804},
{"learn":[4.58952828],"iteration":258,"passed_time":0.2937938172,"remaining_time":0.8405452453},
{"learn":[4.585816572],"iteration":259,"passed_time":0.2942812303,"remaining_time":0.8375696556},
{"learn":[4.582934052],"iteration":260,"passed_time":0.2947680915,"remaining_time":0.8346115693},
{"learn":[4.582234842],"iteration":261,"passed_time":0.2952406978,"remaining_time":0.8316321946},
{"learn":[4.57571562],"iteration":262,"passed_time":0.2957456612,"remaining_time":0.8287625563},
{"learn":[4.571197349],"iteration":263,"passed_time":0.2962462358,"remaining_time":0.8258985967},
{"learn":[4.56723703],"iteration":264,"passed_time":0.2967172549,"remaining_time":0.8229704994},
{"learn":[4.560335567],"iteration":265,"passed_time":0.2972897889,"remaining_time":0.8203409965},
{"learn":[4.554709345],"iteration":266,"passed_time":0.2979198821,"remaining_time":0.8178849197},
{"learn":[4.552806306],"iteration":267,"passed_time":0.2984806282,"remaining_time":0.8152530591},
{"learn":[4.550766241],"iteration":268,"passed_time":0.2990308357,"remaining_time":0.8126079586},
{"learn":[4.549216045],"iteration":269,"passed_time":0.2995618575,"remaining_time":0.8099265036},
{"learn":[4.547687452],"iteration":270,"passed_time":0.3001442161,"remaining_time":0.8073990168},
{"learn":[4.545642435],"iteration":271,"passed_time":0.3006642533,"remaining_time":0.8047190309},
{"learn":[4.543930359],"iteration":272,"passed_time":0.3011944187,"remaining_time":0.8020818403},
{"learn":[4.541029943],"iteration":273,"passed_time":0.3017322223,"remaining_time":0.7994802679},
{"learn":[4.537781449],"iteration":274,"passed_time":0.302332786,"remaining_time":0.7970591631},
{"learn":[4.53066128],"iteration":275,"passed_time":0.302871152,"remaining_time":0.7944880944},
{"learn":[4.526763956],"iteration":276,"passed_time":0.3034190204,"remaining_time":0.7919565045},
{"learn":[4.522036004],"iteration":277,"passed_time":0.3040050163,"remaining_time":0.7895382079},
{"learn":[4.515307629],"iteration":278,"passed_time":0.3045751938,"remaining_time":0.7870921675},
{"learn":[4.51109143],"iteration":279,"passed_time":0.3051529927,"remaining_time":0.7846791241},
{"learn":[4.508233494],"iteration":280,"passed_time":0.3057110268,"remaining_time":0.7822285704},
{"learn":[4.502555629],"iteration":281,"passed_time":0.306254409,"remaining_time":0.7797541335},
{"learn":[4.500081355],"iteration":282,"passed_time":0.3067888344,"remaining_time":0.777270651},
{"learn":[4.495281743],"iteration":283,"passed_time":0.3073304616,"remaining_time":0.774819051},
{"learn":[4.492138869],"iteration":284,"passed_time":0.3078371335,"remaining_time":0.7722931596},
{"learn":[4.491708261],"iteration":285,"passed_time":0.3084201687,"remaining_time":0.7699720297},
{"learn":[4.489398865],"iteration":286,"passed_time":0.3089237066,"remaining_time":0.7674655149},
{"learn":[4.485796373],"iteration":287,"passed_time":0.309496565,"remaining_time":0.7651442857},
{"learn":[4.479542205],"iteration":288,"passed_time":0.31003483,"remaining_time":0.7627500489},
{"learn":[4.475986993],"iteration":289,"passed_time":0.3105830181,"remaining_time":0.7603929064},
{"learn":[4.468661855],"iteration":290,"passed_time":0.3112676479,"remaining_time":0.7583806266},
{"learn":[4.463785664],"iteration":291,"passed_time":0.3119495092,"remaining_time":0.7563707279},
{"learn":[4.460445831],"iteration":292,"passed_time":0.3125776676,"remaining_time":0.7542403104},
{"learn":[4.45692492],"iteration":293,"passed_time":0.3131965958,"remaining_time":0.7520979477},
{"learn":[4.454031688],"iteration":294,"passed_time":0.3137941285,"remaining_time":0.7499147816},
{"learn":[4.451672391],"iteration":295,"passed_time":0.3143955147,"remaining_time":0.7477514943},
{"learn":[4.45031553],"iteration":296,"passed_time":0.3149669718,"remaining_time":0.7455278827},
{"learn":[4.446782666],"iteration":297,"passed_time":0.3155285304,"remaining_time":0.7432920414},
{"learn":[4.444369689],"iteration":298,"passed_time":0.3161874125,"remaining_time":0.7412955725},
{"learn":[4.44411683],"iteration":299,"passed_time":0.3166893289,"remaining_time":0.7389417673},
{"learn":[4.440876943],"iteration":300,"passed_time":0.3172539653,"remaining_time":0.7367459193},
{"learn":[4.439336453],"iteration":301,"passed_time":0.3178206057,"remaining_time":0.7345655059},
{"learn":[4.436666901],"iteration":302,"passed_time":0.3184109905,"remaining_time":0.7324503642},
{"learn":[4.433043336],"iteration":303,"passed_time":0.3190085206,"remaining_time":0.730361613},
{"learn":[4.431419305],"iteration":304,"passed_time":0.3196043929,"remaining_time":0.7282788625},
{"learn":[4.428859646],"iteration":305,"passed_time":0.3202130391,"remaining_time":0.726234801},
{"learn":[4.424552441],"iteration":306,"passed_time":0.3208275535,"remaining_time":0.7242133374},
{"learn":[4.422706391],"iteration":307,"passed_time":0.3213953476,"remaining_time":0.7220960408},
{"learn":[4.421427994],"iteration":308,"passed_time":0.3219647204,"remaining_time":0.7199923036},
{"learn":[4.418733158],"iteration":309,"passed_time":0.3225218078,"remaining_time":0.7178711206},
{"learn":[4.415656941],"iteration":310,"passed_time":0.3231408602,"remaining_time":0.7158972756},
{"learn":[4.410747417],"iteration":311,"passed_time":0.3237535359,"remaining_time":0.7139180535},
{"learn":[4.408126521],"iteration":312,"passed_time":0.3244060962,"remaining_time":0.7120351057},
{"learn":[4.407843853],"iteration":313,"passed_time":0.324976962,"remaining_time":0.7099815157},
{"learn":[4.405219398],"iteration":314,"passed_time":0.3255822139,"remaining_time":0.7080121159},
{"learn":[4.402708465],"iteration":315,"passed_time":0.3262197126,"remaining_time":0.70612115},
{"learn":[4.40104971],"iteration":316,"passed_time":0.3268605845,"remaining_time":0.7042453603},
{"learn":[4.400830038],"iteration":317,"passed_time":0.3274409127,"remaining_time":0.702247492},
{"learn":[4.39784288],"iteration":318,"passed_time":0.327963482,"remaining_time":0.7001352076},
{"learn":[4.393741845],"iteration":319,"passed_time":0.3285116701,"remaining_time":0.698087299},
{"learn":[4.393425936],"iteration":320,"passed_time":0.3291036382,"remaining_time":0.6961413405},
{"learn":[4.390505974],"iteration":321,"passed_time":0.3296823277,"remaining_time":0.694175833},
{"learn":[4.390305136],"iteration":322,"passed_time":0.3302492094,"remaining_time":0.6921941634},
{"learn":[4.38568203],"iteration":323,"passed_time":0.3308780432,"remaining_time":0.6903504853},
{"learn":[4.383057135],"iteration":324,"passed_time":0.331494034,"remaining_time":0.688487609},
{"learn":[4.380662684],"iteration":325,"passed_time":0.3320539015,"remaining_time":0.6865163485},
{"learn":[4.37805727],"iteration":326,"passed_time":0.3326196438,"remaining_time":0.6845658112},
{"learn":[4.373708319],"iteration":327,"passed_time":0.3331707962,"remaining_time":0.6825938263},
{"learn":[4.36887921],"iteration":328,"passed_time":0.333812502,"remaining_time":0.6808151637},
{"learn":[4.367895929],"iteration":329,"passed_time":0.3343654601,"remaining_time":0.6788632068},
{"learn":[4.362140573],"iteration":330,"passed_time":0.3349423904,"remaining_time":0.6769681547},
{"learn":[4.361931924],"iteration":331,"passed_time":0.335559583,"remaining_time":0.6751620525},
{"learn":[4.359656377],"iteration":332,"passed_time":0.3361661873,"remaining_time":0.6733418827},
{"learn":[4.354281355],"iteration":333,"passed_time":0.33682226,"remaining_time":0.6716276202},
{"learn":[4.348589447],"iteration":334,"passed_time":0.3373714009,"remaining_time":0.6697074077},
{"learn":[4.346355698],"iteration":335,"passed_time":0.3379504477,"remaining_time":0.6678544561},
{"learn":[4.343894047],"iteration":336,"passed_time":0.3385221139,"remaining_time":0.6659945445},
{"learn":[4.341561356],"iteration":337,"passed_time":0.3390853443,"remaining_time":0.6641257336},
{"learn":[4.338869061],"iteration":338,"passed_time":0.3396984603,"remaining_time":0.6623618946},
{"learn":[4.333720063],"iteration":339,"passed_time":0.340335701,"remaining_time":0.6606516549},
{"learn":[4.330892223],"iteration":340,"passed_time":0.3409442597,"remaining_time":0.6588922791},
{"learn":[4.328311474],"iteration":341,"passed_time":0.3415955807,"remaining_time":0.6572219068},
{"learn":[4.324580133],"iteration":342,"passed_time":0.3421634855,"remaining_time":0.6553976966},
{"learn":[4.323354432],"iteration":343,"passed_time":0.3427072908,"remaining_time":0.6535348337},
{"learn":[4.323159553],"iteration":344,"passed_time":0.3433034115,"remaining_time":0.6517789406},
{"learn":[4.318639682],"iteration":345,"passed_time":0.3438597645,"remaining_time":0.6499545837},
{"learn":[4.312712208],"iteration":346,"passed_time":0.3444975825,"remaining_time":0.6482908398},
{"learn":[4.311461062],"iteration":347,"passed_time":0.3451261377,"remaining_time":0.6466156373},
{"learn":[4.311178356],"iteration":348,"passed_time":0.3456533177,"remaining_time":0.6447573348},
{"learn":[4.311102505],"iteration":349,"passed_time":0.3462541794,"remaining_time":0.643043476},
{"learn":[4.310232308],"iteration":350,"passed_time":0.3468077316,"remaining_time":0.6412484837},
{"learn":[4.305128197],"iteration":351,"passed_time":0.3473487903,"remaining_time":0.6394375458},
{"learn":[4.304595496],"iteration":352,"passed_time":0.3478794632,"remaining_time":0.6376147667},
{"learn":[4.3004992],"iteration":353,"passed_time":0.3484553665,"remaining_time":0.635881827},
{"learn":[4.297581524],"iteration":354,"passed_time":0.3489686672,"remaining_time":0.6340416629},
{"learn":[4.297355825],"iteration":355,"passed_time":0.3495338017,"remaining_time":0.63230272},
{"learn":[4.295758715],"iteration":356,"passed_time":0.3501753417,"remaining_time":0.6307079683},
{"learn":[4.292500657],"iteration":357,"passed_time":0.3507629709,"remaining_time":0.629021864},
{"learn":[4.290797586],"iteration":358,"passed_time":0.3513198531,"remaining_time":0.6272869801},
{"learn":[4.286410608],"iteration":359,"passed_time":0.3519834673,"remaining_time":0.6257483863},
{"learn":[4.280278245],"iteration":360,"passed_time":0.3525993421,"remaining_time":0.6241301373},
{"learn":[4.279941283],"iteration":361,"passed_time":0.353152142,"remaining_time":0.6224062613},
{"learn":[4.274426275],"iteration":362,"passed_time":0.3538367082,"remaining_time":0.6209200637},
{"learn":[4.273567658],"iteration":363,"passed_time":0.3546235027,"remaining_time":0.6196168894},
{"learn":[4.269488271],"iteration":364,"passed_time":0.3553733184,"remaining_time":0.6182522114},
{"learn":[4.266838205],"iteration":365,"passed_time":0.3560352893,"remaining_time":0.6167387252},
{"learn":[4.263456509],"iteration":366,"passed_time":0.3566375041,"remaining_time":0.6151268123},
{"learn":[4.260360204],"iteration":367,"passed_time":0.3571539232,"remaining_time":0.6133730421},
{"learn":[4.255120549],"iteration":368,"passed_time":0.3577827514,"remaining_time":0.6118182008},
{"learn":[4.252582211],"iteration":369,"passed_time":0.3584359126,"remaining_time":0.6103097971},
{"learn":[4.247857931],"iteration":370,"passed_time":0.3590302083,"remaining_time":0.6087062023},
{"learn":[4.245288911],"iteration":371,"passed_time":0.3596317059,"remaining_time":0.6071201916},
{"learn":[4.24048515],"iteration":372,"passed_time":0.3602485491,"remaining_time":0.6055652554},
{"learn":[4.2378365],"iteration":373,"passed_time":0.3608571082,"remaining_time":0.6040014698},
{"learn":[4.236751063],"iteration":374,"passed_time":0.361439212,"remaining_time":0.6023986867},
{"learn":[4.233240093],"iteration":375,"passed_time":0.3620053026,"remaining_time":0.6007747575},
{"learn":[4.230358421],"iteration":376,"passed_time":0.3625967725,"remaining_time":0.59919838},
{"learn":[4.225853583],"iteration":377,"passed_time":0.3631733906,"remaining_time":0.597602775},
{"learn":[4.224702126],"iteration":378,"passed_time":0.3637979466,"remaining_time":0.5960910946},
{"learn":[4.224361982],"iteration":379,"passed_time":0.364351644,"remaining_time":0.5944684718},
{"learn":[4.223787954],"iteration":380,"passed_time":0.364905953,"remaining_time":0.5928524539},
{"learn":[4.22144054],"iteration":381,"passed_time":0.3655003551,"remaining_time":0.5913068572},
{"learn":[4.217739335],"iteration":382,"passed_time":0.3660690042,"remaining_time":0.5897247405},
{"learn":[4.215611665],"iteration":383,"passed_time":0.3666411472,"remaining_time":0.5881535069},
{"learn":[4.210236863],"iteration":384,"passed_time":0.36725842,"remaining_time":0.5866595541},
{"learn":[4.208454294],"iteration":385,"passed_time":0.3684310799,"remaining_time":0.5860535831},
{"learn":[4.207446501],"iteration":386,"passed_time":0.3690790302,"remaining_time":0.5846135542},
{"learn":[4.204985442],"iteration":387,"passed_time":0.3696521102,"remaining_time":0.583059514},
{"learn":[4.202796622],"iteration":388,"passed_time":0.370232599,"remaining_time":0.5815221542},
{"learn":[4.199774004],"iteration":389,"passed_time":0.3708636941,"remaining_time":0.5800688549},
{"learn":[4.199458358],"iteration":390,"passed_time":0.3714650015,"remaining_time":0.5785733655},
{"learn":[4.19751254],"iteration":391,"passed_time":0.3721175557,"remaining_time":0.5771619231},
{"learn":[4.195201346],"iteration":392,"passed_time":0.3727274551,"remaining_time":0.5756884612},
{"learn":[4.190593508],"iteration":393,"passed_time":0.3733412612,"remaining_time":0.5742253916},
{"learn":[4.187212054],"iteration":394,"passed_time":0.3739380852,"remaining_time":0.5727406115},
{"learn":[4.184984466],"iteration":395,"passed_time":0.3745445771,"remaining_time":0.5712750621},
{"learn":[4.182832144],"iteration":396,"passed_time":0.3752248202,"remaining_time":0.5699258604},
{"learn":[4.179752812],"iteration":397,"passed_time":0.3758520076,"remaining_time":0.5684997702},
{"learn":[4.17878934],"iteration":398,"passed_time":0.3764818937,"remaining_time":0.5670817497},
{"learn":[4.174548229],"iteration":399,"passed_time":0.3770928758,"remaining_time":0.5656393137},
{"learn":[4.168872556],"iteration":400,"passed_time":0.3776839168,"remaining_time":0.5641712373},
{"learn":[4.163926494],"iteration":401,"passed_time":0.378333577,"remaining_time":0.562794724},
{"learn":[4.159485076],"iteration":402,"passed_time":0.3789129935,"remaining_time":0.5613177596},
{"learn":[4.155926102],"iteration":403,"passed_time":0.3795535207,"remaining_time":0.5599353919},
{"learn":[4.153540115],"iteration":404,"passed_time":0.380158506,"remaining_time":0.5585044718},
{"learn":[4.150983044],"iteration":405,"passed_time":0.3807731914,"remaining_time":0.557091812},
{"learn":[4.146539132],"iteration":406,"passed_time":0.3814602409,"remaining_time":0.5557885082},
{"learn":[4.144869174],"iteration":407,"passed_time":0.3821141069,"remaining_time":0.5544400766},
{"learn":[4.142825962],"iteration":408,"passed_time":0.3828395013,"remaining_time":0.5531983991},
{"learn":[4.142467378],"iteration":409,"passed_time":0.3834953413,"remaining_time":0.5518591497},
{"learn":[4.141800768],"iteration":410,"passed_time":0.3841913897,"remaining_time":0.550580848},
{"learn":[4.140107084],"iteration":411,"passed_time":0.3848586843,"remaining_time":0.5492643359},
{"learn":[4.136243196],"iteration":412,"passed_time":0.3855447682,"remaining_time":0.547977673},
{"learn":[4.133618439],"iteration":413,"passed_time":0.3862447187,"remaining_time":0.546713539},
{"learn":[4.131053025],"iteration":414,"passed_time":0.3869049133,"remaining_time":0.5453960825},
{"learn":[4.128379975],"iteration":415,"passed_time":0.3880342471,"remaining_time":0.5447403853},
{"learn":[4.127068571],"iteration":416,"passed_time":0.3887137076,"remaining_time":0.5434534569},
{"learn":[4.125969877],"iteration":417,"passed_time":0.3893989865,"remaining_time":0.5421775362},
{"learn":[4.123893633],"iteration":418,"passed_time":0.3901343043,"remaining_time":0.5409738205},
{"learn":[4.119643722],"iteration":419,"passed_time":0.3908792561,"remaining_time":0.5397856394},
{"learn":[4.11465686],"iteration":420,"passed_time":0.3915132549,"remaining_time":0.5384469705},
{"learn":[4.111565986],"iteration":421,"passed_time":0.3922115517,"remaining_time":0.5371997083},
{"learn":[4.106322452],"iteration":422,"passed_time":0.3929019363,"remaining_time":0.5359442488},
{"learn":[4.104222175],"iteration":423,"passed_time":0.3936107032,"remaining_time":0.534716427},
{"learn":[4.103008002],"iteration":424,"passed_time":0.3942546768,"remaining_time":0.5334033863},
{"learn":[4.099176337],"iteration":425,"passed_time":0.3950331323,"remaining_time":0.53227469},
{"learn":[4.096525716],"iteration":426,"passed_time":0.3957353137,"remaining_time":0.5310452804},
{"learn":[4.094967724],"iteration":427,"passed_time":0.3964495792,"remaining_time":0.5298344844},
{"learn":[4.094683584],"iteration":428,"passed_time":0.3970725758,"remaining_time":0.528504524},
{"learn":[4.091096563],"iteration":429,"passed_time":0.3977423038,"remaining_time":0.5272397981},
{"learn":[4.089178677],"iteration":430,"passed_time":0.398456771,"remaining_time":0.5260368972},
{"learn":[4.085335077],"iteration":431,"passed_time":0.3991463837,"remaining_time":0.5248035785},
{"learn":[4.084852122],"iteration":432,"passed_time":0.3997518104,"remaining_time":0.5234625323},
{"learn":[4.080322952],"iteration":433,"passed_time":0.4004858611,"remaining_time":0.5222926207},
{"learn":[4.077449519],"iteration":434,"passed_time":0.4011601274,"remaining_time":0.521047062},
{"learn":[4.076568374],"iteration":435,"passed_time":0.4018013862,"remaining_time":0.5197614261},
{"learn":[4.076071793],"iteration":436,"passed_time":0.4024290781,"remaining_time":0.5184612608},
{"learn":[4.075027644],"iteration":437,"passed_time":0.4029956304,"remaining_time":0.5170857175},
{"learn":[4.07020837],"iteration":438,"passed_time":0.4036932075,"remaining_time":0.515881297},
{"learn":[4.06833694],"iteration":439,"passed_time":0.4043772274,"remaining_time":0.5146619257},
{"learn":[4.063936568],"iteration":440,"passed_time":0.405102854,"remaining_time":0.513497722},
{"learn":[4.061734926],"iteration":441,"passed_time":0.405770694,"remaining_time":0.5122625503},
{"learn":[4.060815619],"iteration":442,"passed_time":0.4064836232,"remaining_time":0.5110866323},
{"learn":[4.056407489],"iteration":443,"passed_time":0.4071713442,"remaining_time":0.5098812329},
{"learn":[4.05238936],"iteration":444,"passed_time":0.4079318316,"remaining_time":0.5087689136},
{"learn":[4.049685254],"iteration":445,"passed_time":0.4086017926,"remaining_time":0.5075457244},
{"learn":[4.045162016],"iteration":446,"passed_time":0.409352192,"remaining_time":0.5064245239},
{"learn":[4.042955482],"iteration":447,"passed_time":0.4101616343,"remaining_time":0.5053777279},
{"learn":[4.041467663],"iteration":448,"passed_time":0.4108851531,"remaining_time":0.5042265464},
{"learn":[4.038920476],"iteration":449,"passed_time":0.4116526235,"remaining_time":0.5031309843},
{"learn":[4.036694383],"iteration":450,"passed_time":0.4123535567,"remaining_time":0.5019558816},
{"learn":[4.034999007],"iteration":451,"passed_time":0.4130813201,"remaining_time":0.5008154058},
{"learn":[4.031928018],"iteration":452,"passed_time":0.4138146418,"remaining_time":0.4996834637},
{"learn":[4.028718143],"iteration":453,"passed_time":0.4144751764,"remaining_time":0.4984657408},
{"learn":[4.027401978],"iteration":454,"passed_time":0.4151636501,"remaining_time":0.4972839325},
{"learn":[4.025930598],"iteration":455,"passed_time":0.4158656153,"remaining_time":0.4961203831},
{"learn":[4.021074523],"iteration":456,"passed_time":0.4166603781,"remaining_time":0.4950691144},
{"learn":[4.020268486],"iteration":457,"passed_time":0.4173984836,"remaining_time":0.4939519172},
{"learn":[4.017986361],"iteration":458,"passed_time":0.4181327326,"remaining_time":0.4928318265},
{"learn":[4.014814804],"iteration":459,"passed_time":0.4188646098,"remaining_time":0.4917106289},
{"learn":[4.009704796],"iteration":460,"passed_time":0.4196340667,"remaining_time":0.4906350585},
{"learn":[4.008440457],"iteration":461,"passed_time":0.4204457628,"remaining_time":0.4896100008},
{"learn":[4.004854849],"iteration":462,"passed_time":0.4211704239,"remaining_time":0.4884849193},
{"learn":[4.000898028],"iteration":463,"passed_time":0.4220212549,"remaining_time":0.4875073117},
{"learn":[3.996617985],"iteration":464,"passed_time":0.4228199626,"remaining_time":0.4864702795},
{"learn":[3.995443319],"iteration":465,"passed_time":0.4235877698,"remaining_time":0.4853988607},
{"learn":[3.990771995],"iteration":466,"passed_time":0.4244097362,"remaining_time":0.4843905554},
{"learn":[3.989249359],"iteration":467,"passed_time":0.4251698103,"remaining_time":0.4833126904},
{"learn":[3.986599538],"iteration":468,"passed_time":0.4259304315,"remaining_time":0.4822367999},
{"learn":[3.985628919],"iteration":469,"passed_time":0.4265990504,"remaining_time":0.4810585037},
{"learn":[3.985086112],"iteration":470,"passed_time":0.4271795485,"remaining_time":0.4797833995},
{"learn":[3.98466839],"iteration":471,"passed_time":0.4278682491,"remaining_time":0.4786322787},
{"learn":[3.984233894],"iteration":472,"passed_time":0.4285995999,"remaining_time":0.4775306325},
{"learn":[3.981855845],"iteration":473,"passed_time":0.4293026635,"remaining_time":0.4763991582},
{"learn":[3.978684264],"iteration":474,"passed_time":0.4300323903,"remaining_time":0.4752989577},
{"learn":[3.974361269],"iteration":475,"passed_time":0.4306983643,"remaining_time":0.4741301321},
{"learn":[3.972074049],"iteration":476,"passed_time":0.4313400844,"remaining_time":0.4729368221},
{"learn":[3.97191982],"iteration":477,"passed_time":0.431955947,"remaining_time":0.4717175823},
{"learn":[3.969616848],"iteration":478,"passed_time":0.43273314,"remaining_time":0.470676338},
{"learn":[3.968533527],"iteration":479,"passed_time":0.4334074673,"remaining_time":0.4695247562},
{"learn":[3.967568753],"iteration":480,"passed_time":0.4340901662,"remaining_time":0.4683841918},
{"learn":[3.966232553],"iteration":481,"passed_time":0.4347950318,"remaining_time":0.4672693495},
{"learn":[3.961522393],"iteration":482,"passed_time":0.4354984507,"remaining_time":0.4661546563},
{"learn":[3.955829553],"iteration":483,"passed_time":0.4361727713,"remaining_time":0.4650106404},
{"learn":[3.954248095],"iteration":484,"passed_time":0.4367631161,"remaining_time":0.4637793913},
{"learn":[3.951922606],"iteration":485,"passed_time":0.4374668429,"remaining_time":0.462670694},
{"learn":[3.94978202],"iteration":486,"passed_time":0.4381429823,"remaining_time":0.4615345995},
{"learn":[3.949518999],"iteration":487,"passed_time":0.4387452485,"remaining_time":0.4603228837},
{"learn":[3.945431216],"iteration":488,"passed_time":0.4393577354,"remaining_time":0.4591243411},
{"learn":[3.943249086],"iteration":489,"passed_time":0.4400244235,"remaining_time":0.457984604},
{"learn":[3.941981548],"iteration":490,"passed_time":0.4407210538,"remaining_time":0.4568778338},
{"learn":[3.936600517],"iteration":491,"passed_time":0.4414354971,"remaining_time":0.455791123},
{"learn":[3.934476885],"iteration":492,"passed_time":0.4421917587,"remaining_time":0.4547489283},
{"learn":[3.93045798],"iteration":493,"passed_time":0.442942146,"remaining_time":0.4537018742},
{"learn":[3.925977375],"iteration":494,"passed_time":0.4436389926,"remaining_time":0.4526013965},
{"learn":[3.92457993],"iteration":495,"passed_time":0.4442381482,"remaining_time":0.4514032796},
{"learn":[3.919849146],"iteration":496,"passed_time":0.4448823359,"remaining_time":0.4502531488},
{"learn":[3.919681964],"iteration":497,"passed_time":0.4455318309,"remaining_time":0.4491103998},
{"learn":[3.917633027],"iteration":498,"passed_time":0.4461582121,"remaining_time":0.4479464214},
{"learn":[3.916616419],"iteration":499,"passed_time":0.4468100584,"remaining_time":0.4468100584},
{"learn":[3.912896166],"iteration":500,"passed_time":0.4475508745,"remaining_time":0.4457642442},
{"learn":[3.912769674],"iteration":501,"passed_time":0.4482310637,"remaining_time":0.4446595014},
{"learn":[3.909373788],"iteration":502,"passed_time":0.4489269682,"remaining_time":0.4435719745},
{"learn":[3.906706036],"iteration":503,"passed_time":0.449640686,"remaining_time":0.4425035322},
{"learn":[3.903895664],"iteration":504,"passed_time":0.4503295589,"remaining_time":0.4414121419},
{"learn":[3.902982967],"iteration":505,"passed_time":0.4510342707,"remaining_time":0.4403378058},
{"learn":[3.900905528],"iteration":506,"passed_time":0.4517623618,"remaining_time":0.4392876614},
{"learn":[3.897463465],"iteration":507,"passed_time":0.4525302347,"remaining_time":0.4382773139},
{"learn":[3.895918033],"iteration":508,"passed_time":0.4531669558,"remaining_time":0.4371414053},
{"learn":[3.893921936],"iteration":509,"passed_time":0.4538488229,"remaining_time":0.4360508298},
{"learn":[3.890237934],"iteration":510,"passed_time":0.4544819521,"remaining_time":0.4349152144},
{"learn":[3.887311613],"iteration":511,"passed_time":0.4551031466,"remaining_time":0.4337701866},
{"learn":[3.884869735],"iteration":512,"passed_time":0.4557379261,"remaining_time":0.4326400975},
{"learn":[3.882101231],"iteration":513,"passed_time":0.4563873944,"remaining_time":0.4315258243},
{"learn":[3.88060368],"iteration":514,"passed_time":0.457019402,"remaining_time":0.4303969126},
{"learn":[3.877726076],"iteration":515,"passed_time":0.4576269926,"remaining_time":0.4292470241},
{"learn":[3.874938145],"iteration":516,"passed_time":0.4582477879,"remaining_time":0.4281115697},
{"learn":[3.874340833],"iteration":517,"passed_time":0.4589413344,"remaining_time":0.4270457976},
{"learn":[3.873105224],"iteration":518,"passed_time":0.4596234827,"remaining_time":0.4259708963},
{"learn":[3.869800236],"iteration":519,"passed_time":0.4602538184,"remaining_time":0.4248496786},
{"learn":[3.867932518],"iteration":520,"passed_time":0.460857628,"remaining_time":0.4237059574},
{"learn":[3.866666962],"iteration":521,"passed_time":0.4615026517,"remaining_time":0.4226020451},
{"learn":[3.865527652],"iteration":522,"passed_time":0.4621919875,"remaining_time":0.4215403022},
{"learn":[3.861900081],"iteration":523,"passed_time":0.462882922,"remaining_time":0.4204814329},
{"learn":[3.858502887],"iteration":524,"passed_time":0.4635234899,"remaining_time":0.4193783956},
{"learn":[3.858335097],"iteration":525,"passed_time":0.4641707122,"remaining_time":0.4182831132},
{"learn":[3.855719306],"iteration":526,"passed_time":0.4648331049,"remaining_time":0.4172031473},
{"learn":[3.855137428],"iteration":527,"passed_time":0.4655227736,"remaining_time":0.4161491461},
{"learn":[3.851985706],"iteration":528,"passed_time":0.4661755034,"remaining_time":0.4150636335},
{"learn":[3.851051809],"iteration":529,"passed_time":0.466791517,"remaining_time":0.4139471943},
{"learn":[3.850679146],"iteration":530,"passed_time":0.4674657583,"remaining_time":0.412884069},
{"learn":[3.848179484],"iteration":531,"passed_time":0.4680815292,"remaining_time":0.4117709693},
{"learn":[3.844551071],"iteration":532,"passed_time":0.4686761493,"remaining_time":0.410641204},
{"learn":[3.841604794],"iteration":533,"passed_time":0.4692675589,"remaining_time":0.4095106413},
{"learn":[3.83969656],"iteration":534,"passed_time":0.4698839489,"remaining_time":0.4084038061},
{"learn":[3.836811463],"iteration":535,"passed_time":0.4704959841,"remaining_time":0.407295031},
{"learn":[3.834182551],"iteration":536,"passed_time":0.4711400765,"remaining_time":0.4062157456},
{"learn":[3.828012842],"iteration":537,"passed_time":0.4717996987,"remaining_time":0.4051514141},
{"learn":[3.826636176],"iteration":538,"passed_time":0.4724501368,"remaining_time":0.4040807293},
{"learn":[3.826189798],"iteration":539,"passed_time":0.4730514795,"remaining_time":0.4029697789},
{"learn":[3.824104738],"iteration":540,"passed_time":0.4736021555,"remaining_time":0.4018177253},
{"learn":[3.82300218],"iteration":541,"passed_time":0.4742503413,"remaining_time":0.4007502884},
{"learn":[3.817146402],"iteration":542,"passed_time":0.4748449207,"remaining_time":0.3996392795},
{"learn":[3.814638044],"iteration":543,"passed_time":0.4755333148,"remaining_time":0.398608808},
{"learn":[3.812979573],"iteration":544,"passed_time":0.4761613679,"remaining_time":0.3975292154},
{"learn":[3.811938825],"iteration":545,"passed_time":0.4767608982,"remaining_time":0.39642756},
{"learn":[3.811479418],"iteration":546,"passed_time":0.4774030651,"remaining_time":0.3953630502},
{"learn":[3.80742981],"iteration":547,"passed_time":0.478017,"remaining_time":0.3942767956},
{"learn":[3.805097043],"iteration":548,"passed_time":0.478585632,"remaining_time":0.3931550456},
{"learn":[3.801577232],"iteration":549,"passed_time":0.4792277874,"remaining_time":0.3920954625},
{"learn":[3.799762083],"iteration":550,"passed_time":0.4798555657,"remaining_time":0.3910256788},
{"learn":[3.796393455],"iteration":551,"passed_time":0.4804841976,"remaining_time":0.3899581894},
{"learn":[3.793486459],"iteration":552,"passed_time":0.481190588,"remaining_time":0.3889551407},
{"learn":[3.792006091],"iteration":553,"passed_time":0.4817962035,"remaining_time":0.3878720338},
{"learn":[3.78932128],"iteration":554,"passed_time":0.4824980009,"remaining_time":0.3868677665},
{"learn":[3.787581812],"iteration":555,"passed_time":0.4831194759,"remaining_time":0.3858004448},
{"learn":[3.785308865],"iteration":556,"passed_time":0.4837560733,"remaining_time":0.3847467513},
{"learn":[3.78465475],"iteration":557,"passed_time":0.4843456419,"remaining_time":0.3836573006},
{"learn":[3.780498869],"iteration":558,"passed_time":0.4849879019,"remaining_time":0.3826112071},
{"learn":[3.778734909],"iteration":559,"passed_time":0.4855424308,"remaining_time":0.3814976242},
{"learn":[3.778652349],"iteration":560,"passed_time":0.4861000895,"remaining_time":0.3803884836},
{"learn":[3.777928006],"iteration":561,"passed_time":0.4867055373,"remaining_time":0.3793185504},
{"learn":[3.776131406],"iteration":562,"passed_time":0.4873064721,"remaining_time":0.3782467643},
{"learn":[3.772925617],"iteration":563,"passed_time":0.4879814285,"remaining_time":0.3772338703},
{"learn":[3.7727745],"iteration":564,"passed_time":0.4886330557,"remaining_time":0.376204211},
{"learn":[3.771763073],"iteration":565,"passed_time":0.4892515575,"remaining_time":0.3751504876},
{"learn":[3.768738162],"iteration":566,"passed_time":0.4898630367,"remaining_time":0.3740929363},
{"learn":[3.767220794],"iteration":567,"passed_time":0.4904597022,"remaining_time":0.373025689},
{"learn":[3.766691102],"iteration":568,"passed_time":0.4910700576,"remaining_time":0.3719704655},
{"learn":[3.766259335],"iteration":569,"passed_time":0.4916197024,"remaining_time":0.3708710035},
{"learn":[3.76116362],"iteration":570,"passed_time":0.4922208124,"remaining_time":0.369812134},
{"learn":[3.758633056],"iteration":571,"passed_time":0.4928204751,"remaining_time":0.368753782},
{"learn":[3.754603809],"iteration":572,"passed_time":0.4934174264,"remaining_time":0.3676950106},
{"learn":[3.754070549],"iteration":573,"passed_time":0.4940257207,"remaining_time":0.3666462666},
{"learn":[3.750534319],"iteration":574,"passed_time":0.4946420501,"remaining_time":0.3656049935},
{"learn":[3.746491516],"iteration":575,"passed_time":0.4952090759,"remaining_time":0.3645289031},
{"learn":[3.744210544],"iteration":576,"passed_time":0.4958036407,"remaining_time":0.3634747661},
{"learn":[3.742929991],"iteration":577,"passed_time":0.4963748805,"remaining_time":0.3624051896},
{"learn":[3.740402992],"iteration":578,"passed_time":0.4969860606,"remaining_time":0.3613663757},
{"learn":[3.739644243],"iteration":579,"passed_time":0.4975689313,"remaining_time":0.3603085365},
{"learn":[3.737529404],"iteration":580,"passed_time":0.4981975168,"remaining_time":0.3592853004},
{"learn":[3.737196923],"iteration":581,"passed_time":0.4987831887,"remaining_time":0.3582325995},
{"learn":[3.733954464],"iteration":582,"passed_time":0.4993804559,"remaining_time":0.3571897944},
{"learn":[3.731608623],"iteration":583,"passed_time":0.5000161979,"remaining_time":0.3561759218},
{"learn":[3.729843952],"iteration":584,"passed_time":0.500566208,"remaining_time":0.3551025236},
{"learn":[3.727223798],"iteration":585,"passed_time":0.501178858,"remaining_time":0.3540751659},
{"learn":[3.725351667],"iteration":586,"passed_time":0.5017946474,"remaining_time":0.3530514299},
{"learn":[3.725026912],"iteration":587,"passed_time":0.5023677035,"remaining_time":0.3519991392},
{"learn":[3.721974565],"iteration":588,"passed_time":0.5029251617,"remaining_time":0.3509375916},
{"learn":[3.720269493],"iteration":589,"passed_time":0.5035344801,"remaining_time":0.3499137913},
{"learn":[3.718907466],"iteration":590,"passed_time":0.5040805047,"remaining_time":0.3488475912},
{"learn":[3.715602912],"iteration":591,"passed_time":0.5046842229,"remaining_time":0.3478229104},
{"learn":[3.714463059],"iteration":592,"passed_time":0.5052263097,"remaining_time":0.3467573492},
{"learn":[3.710802077],"iteration":593,"passed_time":0.5058127139,"remaining_time":0.3457238415},
{"learn":[3.708032435],"iteration":594,"passed_time":0.5063523556,"remaining_time":0.3446600067},
{"learn":[3.703788939],"iteration":595,"passed_time":0.506931057,"remaining_time":0.3436244077},
{"learn":[3.702500944],"iteration":596,"passed_time":0.5075134756,"remaining_time":0.3425928487},
{"learn":[3.698196925],"iteration":597,"passed_time":0.5081478512,"remaining_time":0.3415977193},
{"learn":[3.69658891],"iteration":598,"passed_time":0.5088610087,"remaining_time":0.340656535},
{"learn":[3.696124066],"iteration":599,"passed_time":0.5097246882,"remaining_time":0.3398164588},
{"learn":[3.693537052],"iteration":600,"passed_time":0.5103189803,"remaining_time":0.3387974595},
{"learn":[3.691343275],"iteration":601,"passed_time":0.5109638425,"remaining_time":0.3378133045},
{"learn":[3.690973831],"iteration":602,"passed_time":0.5115982516,"remaining_time":0.3368233929},
{"learn":[3.686151073],"iteration":603,"passed_time":0.5121889044,"remaining_time":0.3358059704},
{"learn":[3.683921982],"iteration":604,"passed_time":0.5128021599,"remaining_time":0.3348047159},
{"learn":[3.679975271],"iteration":605,"passed_time":0.5133849585,"remaining_time":0.33378494},
{"learn":[3.674047638],"iteration":606,"passed_time":0.5140540642,"remaining_time":0.3328224831},
{"learn":[3.673151794],"iteration":607,"passed_time":0.514600154,"remaining_time":0.3317816783},
{"learn":[3.670953108],"iteration":608,"passed_time":0.5152307496,"remaining_time":0.3307967538},
{"learn":[3.6703947],"iteration":609,"passed_time":0.5158149417,"remaining_time":0.3297833234},
{"learn":[3.668433805],"iteration":610,"passed_time":0.5164130225,"remaining_time":0.3287801403},
{"learn":[3.668304956],"iteration":611,"passed_time":0.5169574734,"remaining_time":0.3277442805},
{"learn":[3.667880012],"iteration":612,"passed_time":0.5175005804,"remaining_time":0.3267091755},
{"learn":[3.667282264],"iteration":613,"passed_time":0.518082564,"remaining_time":0.3257001135},
{"learn":[3.664611483],"iteration":614,"passed_time":0.5187117786,"remaining_time":0.3247220077},
{"learn":[3.662543394],"iteration":615,"passed_time":0.5192834273,"remaining_time":0.3237091495},
{"learn":[3.659041959],"iteration":616,"passed_time":0.5198888526,"remaining_time":0.3227186881},
{"learn":[3.656868545],"iteration":617,"passed_time":0.5204997037,"remaining_time":0.3217328266},
{"learn":[3.654785614],"iteration":618,"passed_time":0.5211033598,"remaining_time":0.3207437481},
{"learn":[3.654566096],"iteration":619,"passed_time":0.5216931236,"remaining_time":0.3197473984},
{"learn":[3.651007045],"iteration":620,"passed_time":0.5223021627,"remaining_time":0.3187641218},
{"learn":[3.648921786],"iteration":621,"passed_time":0.5232355107,"remaining_time":0.3179791367},
{"learn":[3.647655706],"iteration":622,"passed_time":0.523859074,"remaining_time":0.3170062133},
{"learn":[3.647241144],"iteration":623,"passed_time":0.524490866,"remaining_time":0.316039368},
{"learn":[3.644195689],"iteration":624,"passed_time":0.5251053066,"remaining_time":0.315063184},
{"learn":[3.642632246],"iteration":625,"passed_time":0.5257436011,"remaining_time":0.314102407},
{"learn":[3.642523322],"iteration":626,"passed_time":0.5262853028,"remaining_time":0.3130851961},
{"learn":[3.641494659],"iteration":627,"passed_time":0.5269353345,"remaining_time":0.3121336695},
{"learn":[3.63976496],"iteration":628,"passed_time":0.5275991172,"remaining_time":0.3111912122},
{"learn":[3.637945652],"iteration":629,"passed_time":0.528228892,"remaining_time":0.3102296667},
{"learn":[3.636233667],"iteration":630,"passed_time":0.5288660439,"remaining_time":0.3092734868},
{"learn":[3.635304404],"iteration":631,"passed_time":0.5294306499,"remaining_time":0.3082760746},
{"learn":[3.632234951],"iteration":632,"passed_time":0.5300363065,"remaining_time":0.3073038301},
{"learn":[3.631630987],"iteration":633,"passed_time":0.5306104809,"remaining_time":0.3063145679},
{"learn":[3.630301009],"iteration":634,"passed_time":0.5311734955,"remaining_time":0.3053201982},
{"learn":[3.629077964],"iteration":635,"passed_time":0.5317442924,"remaining_time":0.3043316391},
{"learn":[3.628004522],"iteration":636,"passed_time":0.5323333901,"remaining_time":0.3033548204},
{"learn":[3.625062876],"iteration":637,"passed_time":0.5329552187,"remaining_time":0.3023977887},
{"learn":[3.624917986],"iteration":638,"passed_time":0.5335716383,"remaining_time":0.3014387503},
{"learn":[3.622887087],"iteration":639,"passed_time":0.534151907,"remaining_time":0.3004604477},
{"learn":[3.621220865],"iteration":640,"passed_time":0.5347689454,"remaining_time":0.2995039803},
{"learn":[3.621143844],"iteration":641,"passed_time":0.5353547982,"remaining_time":0.2985311803},
{"learn":[3.620822821],"iteration":642,"passed_time":0.5359589546,"remaining_time":0.2975697462},
{"learn":[3.619202826],"iteration":643,"passed_time":0.5367233872,"remaining_time":0.2966980215},
{"learn":[3.618204882],"iteration":644,"passed_time":0.5374139634,"remaining_time":0.2957859798},
{"learn":[3.614259666],"iteration":645,"passed_time":0.5380338651,"remaining_time":0.2948358951},
{"learn":[3.613415661],"iteration":646,"passed_time":0.5386918597,"remaining_time":0.2939076144},
{"learn":[3.611096773],"iteration":647,"passed_time":0.5393727516,"remaining_time":0.2929926058},
{"learn":[3.610820695],"iteration":648,"passed_time":0.5400436921,"remaining_time":0.2920729367},
{"learn":[3.609290065],"iteration":649,"passed_time":0.5406838225,"remaining_time":0.2911374429},
{"learn":[3.60897947],"iteration":650,"passed_time":0.5413189307,"remaining_time":0.2902001641},
{"learn":[3.606570702],"iteration":651,"passed_time":0.5419883051,"remaining_time":0.2892821015},
{"learn":[3.606292637],"iteration":652,"passed_time":0.5426256,"remaining_time":0.2883477538},
{"learn":[3.602753838],"iteration":653,"passed_time":0.5432831408,"remaining_time":0.2874250255},
{"learn":[3.599755869],"iteration":654,"passed_time":0.5439701606,"remaining_time":0.2865186342},
{"learn":[3.599509575],"iteration":655,"passed_time":0.5446571106,"remaining_time":0.2856128751},
{"learn":[3.595337722],"iteration":656,"passed_time":0.5452976571,"remaining_time":0.2846835561},
{"learn":[3.595168561],"iteration":657,"passed_time":0.5459548335,"remaining_time":0.2837637584},
{"learn":[3.59290559],"iteration":658,"passed_time":0.5466364186,"remaining_time":0.2828573881},
{"learn":[3.592015928],"iteration":659,"passed_time":0.5472494593,"remaining_time":0.2819163881},
{"learn":[3.590680403],"iteration":660,"passed_time":0.5479721992,"remaining_time":0.2810326407},
{"learn":[3.590361532],"iteration":661,"passed_time":0.5486589143,"remaining_time":0.2801309865},
{"learn":[3.589069739],"iteration":662,"passed_time":0.5494318815,"remaining_time":0.2792738221},
{"learn":[3.585010186],"iteration":663,"passed_time":0.55008664,"remaining_time":0.2783570949},
{"learn":[3.582997552],"iteration":664,"passed_time":0.5507736698,"remaining_time":0.2774574126},
{"learn":[3.582119256],"iteration":665,"passed_time":0.5515422611,"remaining_time":0.2765992721},
{"learn":[3.579019356],"iteration":666,"passed_time":0.5521947457,"remaining_time":0.2756834338},
{"learn":[3.57719559],"iteration":667,"passed_time":0.5528684204,"remaining_time":0.2747789155},
{"learn":[3.574050046],"iteration":668,"passed_time":0.5534635862,"remaining_time":0.2738362437},
{"learn":[3.572204518],"iteration":669,"passed_time":0.5540980963,"remaining_time":0.2729139877},
{"learn":[3.569508025],"iteration":670,"passed_time":0.554755708,"remaining_time":0.2720039165},
{"learn":[3.566268704],"iteration":671,"passed_time":0.5553672325,"remaining_time":0.2710721016},
{"learn":[3.562564052],"iteration":672,"passed_time":0.5559883411,"remaining_time":0.2701458953},
{"learn":[3.561173586],"iteration":673,"passed_time":0.5565545511,"remaining_time":0.2691940411},
{"learn":[3.559551904],"iteration":674,"passed_time":0.5571334338,"remaining_time":0.2682494311},
{"learn":[3.558593054],"iteration":675,"passed_time":0.5577517308,"remaining_time":0.267324794},
{"learn":[3.555647008],"iteration":676,"passed_time":0.5584791488,"remaining_time":0.2664531242},
{"learn":[3.553100059],"iteration":677,"passed_time":0.5591162232,"remaining_time":0.2655389733},
{"learn":[3.55085578],"iteration":678,"passed_time":0.5596797256,"remaining_time":0.264590857},
{"learn":[3.550737965],"iteration":679,"passed_time":0.560252791,"remaining_time":0.2636483722},
{"learn":[3.549408772],"iteration":680,"passed_time":0.5608823274,"remaining_time":0.262733425},
{"learn":[3.547390589],"iteration":681,"passed_time":0.5614746334,"remaining_time":0.2618019552},
{"learn":[3.54723575],"iteration":682,"passed_time":0.5621594294,"remaining_time":0.2609144058},
{"learn":[3.543988891],"iteration":683,"passed_time":0.5628338703,"remaining_time":0.2600226652},
{"learn":[3.543868508],"iteration":684,"passed_time":0.5634440898,"remaining_time":0.2591020267},
{"learn":[3.542752124],"iteration":685,"passed_time":0.564173818,"remaining_time":0.2582369954},
{"learn":[3.541334315],"iteration":686,"passed_time":0.5647476199,"remaining_time":0.2573013174},
{"learn":[3.540208266],"iteration":687,"passed_time":0.565364102,"remaining_time":0.2563860462},
{"learn":[3.537730983],"iteration":688,"passed_time":0.5660336815,"remaining_time":0.2554956095},
{"learn":[3.53419867],"iteration":689,"passed_time":0.566805732,"remaining_time":0.2546518506},
{"learn":[3.532628335],"iteration":690,"passed_time":0.5674411371,"remaining_time":0.2537471945},
{"learn":[3.532204987],"iteration":691,"passed_time":0.5680490957,"remaining_time":0.2528311004},
{"learn":[3.530618147],"iteration":692,"passed_time":0.5686031542,"remaining_time":0.2518920178},
{"learn":[3.528909306],"iteration":693,"passed_time":0.5692536134,"remaining_time":0.25099655},
{"learn":[3.526700678],"iteration":694,"passed_time":0.569873919,"remaining_time":0.2500885544},
{"learn":[3.526439574],"iteration":695,"passed_time":0.5704945815,"remaining_time":0.2491815414},
{"learn":[3.525784216],"iteration":696,"passed_time":0.5711441483,"remaining_time":0.2482879152},
{"learn":[3.524112693],"iteration":697,"passed_time":0.5717841145,"remaining_time":0.2473908347},
{"learn":[3.522813541],"iteration":698,"passed_time":0.5724468127,"remaining_time":0.2465042784},
{"learn":[3.519148203],"iteration":699,"passed_time":0.5730570308,"remaining_time":0.2455958703},
{"learn":[3.517236747],"iteration":700,"passed_time":0.5736432697,"remaining_time":0.2446780851},
{"learn":[3.515603888],"iteration":701,"passed_time":0.5742238192,"remaining_time":0.2437588292},
{"learn":[3.51263524],"iteration":702,"passed_time":0.5748003991,"remaining_time":0.2428388599},
{"learn":[3.51123442],"iteration":703,"passed_time":0.5753702854,"remaining_time":0.2419170518},
{"learn":[3.50828027],"iteration":704,"passed_time":0.5760248911,"remaining_time":0.241031692},
{"learn":[3.508265537],"iteration":705,"passed_time":0.5764294861,"remaining_time":0.2400428738},
{"learn":[3.506774876],"iteration":706,"passed_time":0.5770571135,"remaining_time":0.239148139},
{"learn":[3.50552068],"iteration":707,"passed_time":0.5776663584,"remaining_time":0.2382465772},
{"learn":[3.501973993],"iteration":708,"passed_time":0.5782984695,"remaining_time":0.2373552251},
{"learn":[3.498880354],"iteration":709,"passed_time":0.5789028521,"remaining_time":0.2364532776},
{"learn":[3.497370959],"iteration":710,"passed_time":0.5795597284,"remaining_time":0.2355735042},
{"learn":[3.496050455],"iteration":711,"passed_time":0.5802310469,"remaining_time":0.2347001987},
{"learn":[3.495630067],"iteration":712,"passed_time":0.5807908188,"remaining_time":0.2337825596},
{"learn":[3.49550669],"iteration":713,"passed_time":0.5813818245,"remaining_time":0.2328784339},
{"learn":[3.493652375],"iteration":714,"passed_time":0.5820574404,"remaining_time":0.2320089098},
{"learn":[3.491915684],"iteration":715,"passed_time":0.582665157,"remaining_time":0.2311129952},
{"learn":[3.490303956],"iteration":716,"passed_time":0.5833311631,"remaining_time":0.2302408914},
{"learn":[3.488363853],"iteration":717,"passed_time":0.5839461082,"remaining_time":0.2293493071},
{"learn":[3.485483936],"iteration":718,"passed_time":0.5845949792,"remaining_time":0.2284717512},
{"learn":[3.483763466],"iteration":719,"passed_time":0.5852660068,"remaining_time":0.2276034471},
{"learn":[3.481642352],"iteration":720,"passed_time":0.5858628739,"remaining_time":0.2267069928},
{"learn":[3.479826119],"iteration":721,"passed_time":0.5864260897,"remaining_time":0.2257984113},
{"learn":[3.478588728],"iteration":722,"passed_time":0.5870368463,"remaining_time":0.2249089992},
{"learn":[3.475390887],"iteration":723,"passed_time":0.5875986112,"remaining_time":0.2240016805},
{"learn":[3.472636852],"iteration":724,"passed_time":0.5881789897,"remaining_time":0.2231023754},
{"learn":[3.47061883],"iteration":725,"passed_time":0.5887763486,"remaining_time":0.2222103575},
{"learn":[3.46953149],"iteration":726,"passed_time":0.5894030132,"remaining_time":0.2213301549},
{"learn":[3.467217162],"iteration":727,"passed_time":0.5900450113,"remaining_time":0.2204563778},
{"learn":[3.465686216],"iteration":728,"passed_time":0.590640566,"remaining_time":0.2195659717},
{"learn":[3.462631216],"iteration":729,"passed_time":0.591253698,"remaining_time":0.2186828746},
{"learn":[3.461451053],"iteration":730,"passed_time":0.5919343529,"remaining_time":0.2178253638},
{"learn":[3.458950469],"iteration":731,"passed_time":0.5925702369,"remaining_time":0.2169519446},
{"learn":[3.458072145],"iteration":732,"passed_time":0.593221085,"remaining_time":0.2160846244},
{"learn":[3.454364268],"iteration":733,"passed_time":0.5938413571,"remaining_time":0.2152068134},
{"learn":[3.453243406],"iteration":734,"passed_time":0.5944248459,"remaining_time":0.214316441},
{"learn":[3.453017963],"iteration":735,"passed_time":0.5950434737,"remaining_time":0.2134395069},
{"learn":[3.45201581],"iteration":736,"passed_time":0.5957102196,"remaining_time":0.2125804447},
{"learn":[3.449510107],"iteration":737,"passed_time":0.5963872254,"remaining_time":0.2117255461},
{"learn":[3.447189189],"iteration":738,"passed_time":0.5970176436,"remaining_time":0.2108546752},
{"learn":[3.446423605],"iteration":739,"passed_time":0.5976636101,"remaining_time":0.2099899171},
{"learn":[3.445531987],"iteration":740,"passed_time":0.5982652465,"remaining_time":0.2091102548},
{"learn":[3.445328199],"iteration":741,"passed_time":0.5988443886,"remaining_time":0.2082235205},
{"learn":[3.443327544],"iteration":742,"passed_time":0.5994388274,"remaining_time":0.2073429053},
{"learn":[3.441475798],"iteration":743,"passed_time":0.6001130702,"remaining_time":0.2064905188},
{"learn":[3.439046501],"iteration":744,"passed_time":0.6007167066,"remaining_time":0.2056144432},
{"learn":[3.435899469],"iteration":745,"passed_time":0.6014294773,"remaining_time":0.2047762564},
{"learn":[3.433988352],"iteration":746,"passed_time":0.6020984574,"remaining_time":0.2039235739},
{"learn":[3.433413263],"iteration":747,"passed_time":0.6027677822,"remaining_time":0.2030714988},
{"learn":[3.429944699],"iteration":748,"passed_time":0.6034377764,"remaining_time":0.202220136},
{"learn":[3.429291634],"iteration":749,"passed_time":0.6041103773,"remaining_time":0.2013701258},
{"learn":[3.429175603],"iteration":750,"passed_time":0.604750826,"remaining_time":0.2005099277},
{"learn":[3.428780323],"iteration":751,"passed_time":0.605372468,"remaining_time":0.1996441118},
{"learn":[3.423893341],"iteration":752,"passed_time":0.6062268204,"remaining_time":0.1988552784},
{"learn":[3.421024316],"iteration":753,"passed_time":0.6070120412,"remaining_time":0.1980437164},
{"learn":[3.420969872],"iteration":754,"passed_time":0.6076630703,"remaining_time":0.1971886784},
{"learn":[3.419544785],"iteration":755,"passed_time":0.6083882516,"remaining_time":0.196358113},
{"learn":[3.417057977],"iteration":756,"passed_time":0.6090431928,"remaining_time":0.1955052785},
{"learn":[3.415160245],"iteration":757,"passed_time":0.6097197893,"remaining_time":0.19465988},
{"learn":[3.412854597],"iteration":758,"passed_time":0.6104438312,"remaining_time":0.1938299912},
{"learn":[3.410926347],"iteration":759,"passed_time":0.6111448401,"remaining_time":0.1929931074},
{"learn":[3.408963843],"iteration":760,"passed_time":0.6119076854,"remaining_time":0.1921760011},
{"learn":[3.407629634],"iteration":761,"passed_time":0.6126676868,"remaining_time":0.1913581489},
{"learn":[3.404384724],"iteration":762,"passed_time":0.6134122315,"remaining_time":0.1905356473},
{"learn":[3.403041656],"iteration":763,"passed_time":0.614043605,"remaining_time":0.1896783911},
{"learn":[3.401101731],"iteration":764,"passed_time":0.6146741103,"remaining_time":0.1888214587},
{"learn":[3.400890668],"iteration":765,"passed_time":0.6153157526,"remaining_time":0.1879685197},
{"learn":[3.399289941],"iteration":766,"passed_time":0.6159758059,"remaining_time":0.1871217246},
{"learn":[3.399202366],"iteration":767,"passed_time":0.6166398144,"remaining_time":0.1862766106},
{"learn":[3.397447845],"iteration":768,"passed_time":0.6174542071,"remaining_time":0.1854771415},
{"learn":[3.394655341],"iteration":769,"passed_time":0.6181538507,"remaining_time":0.184643358},
{"learn":[3.393228229],"iteration":770,"passed_time":0.6188256091,"remaining_time":0.1838016401},
{"learn":[3.389691197],"iteration":771,"passed_time":0.6194874427,"remaining_time":0.1829574313},
{"learn":[3.389626772],"iteration":772,"passed_time":0.6200505072,"remaining_time":0.1820846897},
{"learn":[3.388480222],"iteration":773,"passed_time":0.62067381,"remaining_time":0.1812303373},
{"learn":[3.388215066],"iteration":774,"passed_time":0.6213600455,"remaining_time":0.1803948519},
{"learn":[3.386324358],"iteration":775,"passed_time":0.6220478619,"remaining_time":0.1795602075},
{"learn":[3.383913061],"iteration":776,"passed_time":0.6227266993,"remaining_time":0.1787233642},
{"learn":[3.382839768],"iteration":777,"passed_time":0.6233978693,"remaining_time":0.1778847391},
{"learn":[3.381961844],"iteration":778,"passed_time":0.6241602976,"remaining_time":0.1770724336},
{"learn":[3.381521703],"iteration":779,"passed_time":0.6247795027,"remaining_time":0.1762198597},
{"learn":[3.380918963],"iteration":780,"passed_time":0.6253884397,"remaining_time":0.1753650042},
{"learn":[3.377139006],"iteration":781,"passed_time":0.6261631098,"remaining_time":0.1745569795},
{"learn":[3.376004372],"iteration":782,"passed_time":0.6268441215,"remaining_time":0.1737230835},
{"learn":[3.373826468],"iteration":783,"passed_time":0.6275471879,"remaining_time":0.1728956538},
{"learn":[3.373546786],"iteration":784,"passed_time":0.6282864952,"remaining_time":0.1720784668},
{"learn":[3.372109181],"iteration":785,"passed_time":0.6289983042,"remaining_time":0.1712539912},
{"learn":[3.370764924],"iteration":786,"passed_time":0.6296861416,"remaining_time":0.1704233141},
{"learn":[3.367833107],"iteration":787,"passed_time":0.6303747241,"remaining_time":0.1695931999},
{"learn":[3.36450404],"iteration":788,"passed_time":0.631013839,"remaining_time":0.1687502155},
{"learn":[3.361794558],"iteration":789,"passed_time":0.6317237582,"remaining_time":0.1679265686},
{"learn":[3.356880529],"iteration":790,"passed_time":0.6324471924,"remaining_time":0.1671067803},
{"learn":[3.353843509],"iteration":791,"passed_time":0.633092613,"remaining_time":0.1662667468},
{"learn":[3.353640253],"iteration":792,"passed_time":0.6337484919,"remaining_time":0.1654299342},
{"learn":[3.353055088],"iteration":793,"passed_time":0.6344680098,"remaining_time":0.1646100882},
{"learn":[3.351415617],"iteration":794,"passed_time":0.6351647394,"remaining_time":0.1637846183},
{"learn":[3.349169061],"iteration":795,"passed_time":0.635794304,"remaining_time":0.1629422588},
{"learn":[3.346211014],"iteration":796,"passed_time":0.636445797,"remaining_time":0.1621060186},
{"learn":[3.344560452],"iteration":797,"passed_time":0.6370477781,"remaining_time":0.1612577082},
{"learn":[3.344445461],"iteration":798,"passed_time":0.637669621,"remaining_time":0.160415011},
{"learn":[3.342608898],"iteration":799,"passed_time":0.6384315479,"remaining_time":0.159607887},
{"learn":[3.339572899],"iteration":800,"passed_time":0.6391896622,"remaining_time":0.1587999286},
{"learn":[3.339309302],"iteration":801,"passed_time":0.6397693042,"remaining_time":0.1579480327},
{"learn":[3.33698088],"iteration":802,"passed_time":0.6404638285,"remaining_time":0.157124999},
{"learn":[3.334746342],"iteration":803,"passed_time":0.6410989688,"remaining_time":0.1562878083},
{"learn":[3.332048511],"iteration":804,"passed_time":0.6417174885,"remaining_time":0.1554470935},
{"learn":[3.331932544],"iteration":805,"passed_time":0.6423910864,"remaining_time":0.1546201871},
{"learn":[3.330541133],"iteration":806,"passed_time":0.64297647,"remaining_time":0.1537725635},
{"learn":[3.329124989],"iteration":807,"passed_time":0.6435734353,"remaining_time":0.1529283411},
{"learn":[3.32583918],"iteration":808,"passed_time":0.6442461833,"remaining_time":0.1521026218},
{"learn":[3.325287299],"iteration":809,"passed_time":0.6448610292,"remaining_time":0.1512636982},
{"learn":[3.322745162],"iteration":810,"passed_time":0.6455241036,"remaining_time":0.1504365667},
{"learn":[3.319733662],"iteration":811,"passed_time":0.6461312538,"remaining_time":0.1495968913},
{"learn":[3.318080007],"iteration":812,"passed_time":0.6467881516,"remaining_time":0.1487692304},
{"learn":[3.317179538],"iteration":813,"passed_time":0.6474326351,"remaining_time":0.1479391525},
{"learn":[3.315685949],"iteration":814,"passed_time":0.6481204718,"remaining_time":0.1471193709},
{"learn":[3.314944576],"iteration":815,"passed_time":0.6487562719,"remaining_time":0.146288179},
{"learn":[3.312369052],"iteration":816,"passed_time":0.649506717,"remaining_time":0.1454831447},
{"learn":[3.312321621],"iteration":817,"passed_time":0.6499610273,"remaining_time":0.1446123557},
{"learn":[3.309465776],"iteration":818,"passed_time":0.6506280205,"remaining_time":0.1437895869},
{"learn":[3.308307377],"iteration":819,"passed_time":0.6512798681,"remaining_time":0.1429638735},
{"learn":[3.308076804],"iteration":820,"passed_time":0.6518325635,"remaining_time":0.1421169657},
{"learn":[3.305643326],"iteration":821,"passed_time":0.6524207958,"remaining_time":0.1412784692},
{"learn":[3.304154814],"iteration":822,"passed_time":0.6529972298,"remaining_time":0.1404380433},
{"learn":[3.303076321],"iteration":823,"passed_time":0.6535362513,"remaining_time":0.1395902673},
{"learn":[3.301746372],"iteration":824,"passed_time":0.6541530007,"remaining_time":0.1387597274},
{"learn":[3.301345455],"iteration":825,"passed_time":0.6547044132,"remaining_time":0.1379159418},
{"learn":[3.299181039],"iteration":826,"passed_time":0.6553234713,"remaining_time":0.137087014},
{"learn":[3.297989357],"iteration":827,"passed_time":0.6559623396,"remaining_time":0.1362627082},
{"learn":[3.294775182],"iteration":828,"passed_time":0.6566240982,"remaining_time":0.1354435715},
{"learn":[3.293840636],"iteration":829,"passed_time":0.6572532725,"remaining_time":0.1346181401},
{"learn":[3.289279397],"iteration":830,"passed_time":0.6578898798,"remaining_time":0.1337946928},
{"learn":[3.286204979],"iteration":831,"passed_time":0.6584836149,"remaining_time":0.1329630376},
{"learn":[3.284833593],"iteration":832,"passed_time":0.6591361385,"remaining_time":0.1321437396},
{"learn":[3.283519914],"iteration":833,"passed_time":0.6597090554,"remaining_time":0.1313089966},
{"learn":[3.282853026],"iteration":834,"passed_time":0.6603741327,"remaining_time":0.1304930921},
{"learn":[3.281944673],"iteration":835,"passed_time":0.6610388128,"remaining_time":0.1296774704},
{"learn":[3.279764865],"iteration":836,"passed_time":0.6618470864,"remaining_time":0.1288901733},
{"learn":[3.277468839],"iteration":837,"passed_time":0.6625451163,"remaining_time":0.1280815141},
{"learn":[3.277124974],"iteration":838,"passed_time":0.6632142712,"remaining_time":0.1272675777},
{"learn":[3.275636037],"iteration":839,"passed_time":0.6638250991,"remaining_time":0.126442876},
{"learn":[3.274413635],"iteration":840,"passed_time":0.6645039351,"remaining_time":0.1256315407},
{"learn":[3.272636087],"iteration":841,"passed_time":0.6651004069,"remaining_time":0.1248050645},
{"learn":[3.269644466],"iteration":842,"passed_time":0.6657226716,"remaining_time":0.1239839377},
{"learn":[3.26852083],"iteration":843,"passed_time":0.6663183933,"remaining_time":0.123158376},
{"learn":[3.267820927],"iteration":844,"passed_time":0.6669194519,"remaining_time":0.1223343373},
{"learn":[3.267331099],"iteration":845,"passed_time":0.6674905108,"remaining_time":0.1215053649},
{"learn":[3.267231014],"iteration":846,"passed_time":0.6681143424,"remaining_time":0.1206865341},
{"learn":[3.267158695],"iteration":847,"passed_time":0.6686591013,"remaining_time":0.1198539898},
{"learn":[3.264718705],"iteration":848,"passed_time":0.6692692751,"remaining_time":0.119033758},
{"learn":[3.261678512],"iteration":849,"passed_time":0.6698624582,"remaining_time":0.118211022},
{"learn":[3.261368381],"iteration":850,"passed_time":0.6704548341,"remaining_time":0.1173886842},
{"learn":[3.260128799],"iteration":851,"passed_time":0.6712233169,"remaining_time":0.1165974776},
{"learn":[3.258972952],"iteration":852,"passed_time":0.6719158693,"remaining_time":0.1157932389},
{"learn":[3.258724846],"iteration":853,"passed_time":0.6725846784,"remaining_time":0.1149852026},
{"learn":[3.25686724],"iteration":854,"passed_time":0.6732047193,"remaining_time":0.1141692214},
{"learn":[3.255750259],"iteration":855,"passed_time":0.6738589949,"remaining_time":0.1133594571},
{"learn":[3.254915866],"iteration":856,"passed_time":0.6745305268,"remaining_time":0.112552935},
{"learn":[3.254348625],"iteration":857,"passed_time":0.6751861777,"remaining_time":0.1117440993},
{"learn":[3.253408514],"iteration":858,"passed_time":0.6758524896,"remaining_time":0.1109373702},
{"learn":[3.253291714],"iteration":859,"passed_time":0.6764486955,"remaining_time":0.1101195551},
{"learn":[3.250186342],"iteration":860,"passed_time":0.6771107396,"remaining_time":0.1093128836},
{"learn":[3.249141318],"iteration":861,"passed_time":0.677790703,"remaining_time":0.1085094165},
{"learn":[3.246300388],"iteration":862,"passed_time":0.6784795138,"remaining_time":0.1077076401},
{"learn":[3.245205135],"iteration":863,"passed_time":0.6791396917,"remaining_time":0.1069016181},
{"learn":[3.244403535],"iteration":864,"passed_time":0.6797415628,"remaining_time":0.1060868335},
{"learn":[3.244211781],"iteration":865,"passed_time":0.6803867504,"remaining_time":0.1052792431},
{"learn":[3.242286347],"iteration":866,"passed_time":0.6810226115,"remaining_time":0.1044705967},
{"learn":[3.239606746],"iteration":867,"passed_time":0.681696475,"remaining_time":0.1036681275},
{"learn":[3.236773361],"iteration":868,"passed_time":0.682355613,"remaining_time":0.1028637345},
{"learn":[3.234552446],"iteration":869,"passed_time":0.6830403366,"remaining_time":0.1020634986},
{"learn":[3.233724647],"iteration":870,"passed_time":0.6837406945,"remaining_time":0.1012658434},
{"learn":[3.230851485],"iteration":871,"passed_time":0.684369508,"remaining_time":0.1004579094},
{"learn":[3.227728941],"iteration":872,"passed_time":0.6850603564,"remaining_time":0.09965941039},
{"learn":[3.225787575],"iteration":873,"passed_time":0.6858159501,"remaining_time":0.09887049166},
{"learn":[3.222797487],"iteration":874,"passed_time":0.6865261915,"remaining_time":0.09807517021},
{"learn":[3.22137014],"iteration":875,"passed_time":0.6872103074,"remaining_time":0.09727634488},
{"learn":[3.219701963],"iteration":876,"passed_time":0.6879155608,"remaining_time":0.0964807457},
{"learn":[3.21783327],"iteration":877,"passed_time":0.688551888,"remaining_time":0.09567577487},
{"learn":[3.217713355],"iteration":878,"passed_time":0.6892253693,"remaining_time":0.09487630226},
{"learn":[3.217666091],"iteration":879,"passed_time":0.6898868521,"remaining_time":0.09407547983},
{"learn":[3.214962005],"iteration":880,"passed_time":0.6906025393,"remaining_time":0.09328229532},
{"learn":[3.214081828],"iteration":881,"passed_time":0.691263576,"remaining_time":0.09248197502},
{"learn":[3.213358337],"iteration":882,"passed_time":0.6918900044,"remaining_time":0.0916773845},
{"learn":[3.210850401],"iteration":883,"passed_time":0.6925750623,"remaining_time":0.09088089053},
{"learn":[3.207810328],"iteration":884,"passed_time":0.6934479772,"remaining_time":0.09010905919},
{"learn":[3.204935073],"iteration":885,"passed_time":0.6941519546,"remaining_time":0.08931526279},
{"learn":[3.20280198],"iteration":886,"passed_time":0.6948935347,"remaining_time":0.08852645932},
{"learn":[3.200663495],"iteration":887,"passed_time":0.6956092162,"remaining_time":0.08773449573},
{"learn":[3.197301669],"iteration":888,"passed_time":0.6962809607,"remaining_time":0.08693721781},
{"learn":[3.195666943],"iteration":889,"passed_time":0.6969934474,"remaining_time":0.08614525754},
{"learn":[3.193886506],"iteration":890,"passed_time":0.6976280299,"remaining_time":0.0853439453},
{"learn":[3.190601248],"iteration":891,"passed_time":0.6983264113,"remaining_time":0.08455073142},
{"learn":[3.188983797],"iteration":892,"passed_time":0.6988752963,"remaining_time":0.08373981714},
{"learn":[3.187365749],"iteration":893,"passed_time":0.6995654497,"remaining_time":0.082946239},
{"learn":[3.186160771],"iteration":894,"passed_time":0.7002261071,"remaining_time":0.08214943156},
{"learn":[3.185358981],"iteration":895,"passed_time":0.7008628832,"remaining_time":0.08135015608},
{"learn":[3.183832164],"iteration":896,"passed_time":0.7015095027,"remaining_time":0.08055237322},
{"learn":[3.183106966],"iteration":897,"passed_time":0.7021102855,"remaining_time":0.07974972063},
{"learn":[3.182838152],"iteration":898,"passed_time":0.7026832599,"remaining_time":0.07894439294},
{"learn":[3.180835453],"iteration":899,"passed_time":0.7033267129,"remaining_time":0.07814741254},
{"learn":[3.179957348],"iteration":900,"passed_time":0.7039750985,"remaining_time":0.07735131493},
{"learn":[3.179752966],"iteration":901,"passed_time":0.7046548937,"remaining_time":0.07655895741},
{"learn":[3.178851983],"iteration":902,"passed_time":0.7053459053,"remaining_time":0.07576805405},
{"learn":[3.176748586],"iteration":903,"passed_time":0.7060094973,"remaining_time":0.0749744599},
{"learn":[3.172960988],"iteration":904,"passed_time":0.7067523321,"remaining_time":0.07418947132},
{"learn":[3.172794225],"iteration":905,"passed_time":0.70736312,"remaining_time":0.07339087558},
{"learn":[3.169996507],"iteration":906,"passed_time":0.7080152642,"remaining_time":0.07259693448},
{"learn":[3.16813015],"iteration":907,"passed_time":0.7087429956,"remaining_time":0.07181096431},
{"learn":[3.166920871],"iteration":908,"passed_time":0.7094072535,"remaining_time":0.07101876795},
{"learn":[3.16531606],"iteration":909,"passed_time":0.709972968,"remaining_time":0.07021710672},
{"learn":[3.162035247],"iteration":910,"passed_time":0.7105985124,"remaining_time":0.06942180857},
{"learn":[3.16189467],"iteration":911,"passed_time":0.7112036929,"remaining_time":0.06862491774},
{"learn":[3.161008416],"iteration":912,"passed_time":0.7118109685,"remaining_time":0.0678286465},
{"learn":[3.160560787],"iteration":913,"passed_time":0.7124553289,"remaining_time":0.06703627821},
{"learn":[3.160416261],"iteration":914,"passed_time":0.7130793903,"remaining_time":0.06624234773},
{"learn":[3.15844291],"iteration":915,"passed_time":0.7136863279,"remaining_time":0.06544721784},
{"learn":[3.155040501],"iteration":916,"passed_time":0.71426034,"remaining_time":0.06464951823},
{"learn":[3.154937548],"iteration":917,"passed_time":0.7148845645,"remaining_time":0.06385679116},
{"learn":[3.153721161],"iteration":918,"passed_time":0.7155577439,"remaining_time":0.06306874565},
{"learn":[3.153170511],"iteration":919,"passed_time":0.7161643721,"remaining_time":0.06227516279},
{"learn":[3.153113601],"iteration":920,"passed_time":0.7167436002,"remaining_time":0.06147963563},
{"learn":[3.150607379],"iteration":921,"passed_time":0.7173563136,"remaining_time":0.06068741048},
{"learn":[3.148408359],"iteration":922,"passed_time":0.7179734619,"remaining_time":0.05989594428},
{"learn":[3.147495728],"iteration":923,"passed_time":0.7186137708,"remaining_time":0.05910676037},
{"learn":[3.146946235],"iteration":924,"passed_time":0.7192253994,"remaining_time":0.05831557293},
{"learn":[3.14472738],"iteration":925,"passed_time":0.7198663823,"remaining_time":0.05752711911},
{"learn":[3.144469477],"iteration":926,"passed_time":0.7205058879,"remaining_time":0.05673886712},
{"learn":[3.142975516],"iteration":927,"passed_time":0.7212105001,"remaining_time":0.05595598708},
{"learn":[3.14079113],"iteration":928,"passed_time":0.7218928739,"remaining_time":0.05517157594},
{"learn":[3.138173032],"iteration":929,"passed_time":0.722524378,"remaining_time":0.05438355533},
{"learn":[3.136352813],"iteration":930,"passed_time":0.7232005024,"remaining_time":0.05359917794},
{"learn":[3.133735004],"iteration":931,"passed_time":0.7238505009,"remaining_time":0.05281312668},
{"learn":[3.1319496],"iteration":932,"passed_time":0.7245072481,"remaining_time":0.05202785168},
{"learn":[3.129865343],"iteration":933,"passed_time":0.7251214681,"remaining_time":0.05123984678},
{"learn":[3.129830206],"iteration":934,"passed_time":0.7255424636,"remaining_time":0.05043878089},
{"learn":[3.126676562],"iteration":935,"passed_time":0.7261489983,"remaining_time":0.04965121356},
{"learn":[3.12645665],"iteration":936,"passed_time":0.7267546998,"remaining_time":0.04886397662},
{"learn":[3.126378007],"iteration":937,"passed_time":0.7273407211,"remaining_time":0.04807582592},
{"learn":[3.124621914],"iteration":938,"passed_time":0.7279583444,"remaining_time":0.04729015869},
{"learn":[3.123379018],"iteration":939,"passed_time":0.7285922832,"remaining_time":0.04650589042},
{"learn":[3.123332451],"iteration":940,"passed_time":0.729227183,"remaining_time":0.04572200191},
{"learn":[3.122432444],"iteration":941,"passed_time":0.7299028174,"remaining_time":0.0449409378},
{"learn":[3.121889006],"iteration":942,"passed_time":0.7305104809,"remaining_time":0.04415598877},
{"learn":[3.121070914],"iteration":943,"passed_time":0.7311850923,"remaining_time":0.04337538683},
{"learn":[3.118444705],"iteration":944,"passed_time":0.7319666465,"remaining_time":0.0426012334},
{"learn":[3.116820458],"iteration":945,"passed_time":0.7326280865,"remaining_time":0.0418202079},
{"learn":[3.114971041],"iteration":946,"passed_time":0.733343161,"remaining_time":0.04104243668},
{"learn":[3.114685138],"iteration":947,"passed_time":0.7340370804,"remaining_time":0.04026363732},
{"learn":[3.113399363],"iteration":948,"passed_time":0.7346844044,"remaining_time":0.03948251278},
{"learn":[3.110575399],"iteration":949,"passed_time":0.7353197942,"remaining_time":0.0387010418},
{"learn":[3.110466553],"iteration":950,"passed_time":0.7359111024,"remaining_time":0.03791760675},
{"learn":[3.108691641],"iteration":951,"passed_time":0.7365523301,"remaining_time":0.03713709228},
{"learn":[3.107898017],"iteration":952,"passed_time":0.7371440074,"remaining_time":0.03635442639},
{"learn":[3.105551729],"iteration":953,"passed_time":0.7377315227,"remaining_time":0.03557196022},
{"learn":[3.104824945],"iteration":954,"passed_time":0.7383554025,"remaining_time":0.03479161583},
{"learn":[3.103186704],"iteration":955,"passed_time":0.739004075,"remaining_time":0.03401273985},
{"learn":[3.102330655],"iteration":956,"passed_time":0.7397064317,"remaining_time":0.03323654813},
{"learn":[3.102291298],"iteration":957,"passed_time":0.7403139384,"remaining_time":0.03245635221},
{"learn":[3.100363529],"iteration":958,"passed_time":0.7410194699,"remaining_time":0.03168070726},
{"learn":[3.097871596],"iteration":959,"passed_time":0.7416961659,"remaining_time":0.03090400691},
{"learn":[3.097372213],"iteration":960,"passed_time":0.7422754682,"remaining_time":0.03012356219},
{"learn":[3.095981813],"iteration":961,"passed_time":0.7429519655,"remaining_time":0.02934737494},
{"learn":[3.095347452],"iteration":962,"passed_time":0.7435785313,"remaining_time":0.02856947628},
{"learn":[3.094728409],"iteration":963,"passed_time":0.7441992837,"remaining_time":0.02779167449},
{"learn":[3.094118537],"iteration":964,"passed_time":0.7448260907,"remaining_time":0.0270144178},
{"learn":[3.093793695],"iteration":965,"passed_time":0.7455189963,"remaining_time":0.02623979904},
{"learn":[3.092581602],"iteration":966,"passed_time":0.7461712233,"remaining_time":0.02546396108},
{"learn":[3.091694202],"iteration":967,"passed_time":0.7470187724,"remaining_time":0.02469483545},
{"learn":[3.090298312],"iteration":968,"passed_time":0.7478402156,"remaining_time":0.02392471278},
{"learn":[3.090020107],"iteration":969,"passed_time":0.7485582994,"remaining_time":0.02315128761},
{"learn":[3.088949869],"iteration":970,"passed_time":0.7492837441,"remaining_time":0.02237819627},
{"learn":[3.086700204],"iteration":971,"passed_time":0.7499842658,"remaining_time":0.02160448502},
{"learn":[3.086584317],"iteration":972,"passed_time":0.7506258928,"remaining_time":0.02082928993},
{"learn":[3.084850742],"iteration":973,"passed_time":0.7513092304,"remaining_time":0.02005548254},
{"learn":[3.084239948],"iteration":974,"passed_time":0.751988023,"remaining_time":0.01928174418},
{"learn":[3.082561673],"iteration":975,"passed_time":0.7527182479,"remaining_time":0.01850946511},
{"learn":[3.07991814],"iteration":976,"passed_time":0.753363822,"remaining_time":0.01773527933},
{"learn":[3.079350277],"iteration":977,"passed_time":0.7540604466,"remaining_time":0.01696250493},
{"learn":[3.077637462],"iteration":978,"passed_time":0.7548361069,"remaining_time":0.01619158146},
{"learn":[3.076733301],"iteration":979,"passed_time":0.7555533749,"remaining_time":0.01541945663},
{"learn":[3.07594065],"iteration":980,"passed_time":0.7562315915,"remaining_time":0.0146466873},
{"learn":[3.072594655],"iteration":981,"passed_time":0.7569305488,"remaining_time":0.01387449071},
{"learn":[3.071977674],"iteration":982,"passed_time":0.7575973643,"remaining_time":0.01310188728},
{"learn":[3.069532634],"iteration":983,"passed_time":0.7582268658,"remaining_time":0.01232889213},
{"learn":[3.068870784],"iteration":984,"passed_time":0.7589509702,"remaining_time":0.01155762899},
{"learn":[3.068801463],"iteration":985,"passed_time":0.7596974447,"remaining_time":0.01078677913},
{"learn":[3.067433249],"iteration":986,"passed_time":0.7603879295,"remaining_time":0.01001524122},
{"learn":[3.065611456],"iteration":987,"passed_time":0.7611959401,"remaining_time":0.009245294819},
{"learn":[3.063039162],"iteration":988,"passed_time":0.7618997673,"remaining_time":0.008474112679},
{"learn":[3.06177873],"iteration":989,"passed_time":0.7624943585,"remaining_time":0.007701963217},
{"learn":[3.061689148],"iteration":990,"passed_time":0.7632940546,"remaining_time":0.006932034805},
{"learn":[3.058984039],"iteration":991,"passed_time":0.7640251917,"remaining_time":0.006161493481},
{"learn":[3.057492984],"iteration":992,"passed_time":0.7647424886,"remaining_time":0.005390933958},
{"learn":[3.057290731],"iteration":993,"passed_time":0.7654345828,"remaining_time":0.004620329474},
{"learn":[3.056068348],"iteration":994,"passed_time":0.7661277054,"remaining_time":0.003849887967},
{"learn":[3.054987307],"iteration":995,"passed_time":0.766830011,"remaining_time":0.003079638598},
{"learn":[3.054200234],"iteration":996,"passed_time":0.7675548887,"remaining_time":0.002309593446},
{"learn":[3.052732869],"iteration":997,"passed_time":0.7682761776,"remaining_time":0.001539631618},
{"learn":[3.051787862],"iteration":998,"passed_time":0.7689874792,"remaining_time":0.0007697572364},
{"learn":[3.051366222],"iteration":999,"passed_time":0.7697061324,"remaining_time":0}
]}